Workbook

Sheet Proforma
A1: ='Room Types'!A1 -> Hotel xxxx
A2: For Discussion Purposes Only
A3: JPY
D5: Proforma | G5: =D5 -> Proforma | J5: =G5 -> Proforma | M5: =J5 -> Proforma | P5: =M5 -> Proforma | S5: (before c tax) | T5: =#REF! -> #REF!
D6: Year 1 | G6: Year 2 | J6: Year 3 | M6: Year 4 | P6: Year 5 | S6: Project Costs | T6: Cost | U6: per room
S8: Purchase Price (inc FF&E) | U8: =ROUND(T8/$P$11,-4) -> 0
B9: KPIs | F9: % Grth | I9: % Grth | L9: % Grth | O9: % Grth | S9: New Signage, etc. | U9: =ROUND(T9/$P$11,-4) -> 0
B10: No of Days | D10: =Rooms!S7 -> 365 | G10: =D10 -> 365 | J10: =G10 -> 365 | M10: =J10 -> 365 | P10: =M10 -> 365 | S10: OSE, etc | U10: =ROUND(T10/$P$11,-4) -> 0
B11: No of Rooms | D11: =Rooms!G8 -> 207 | G11: =D11 -> 207 | J11: =G11 -> 207 | M11: =J11 -> 207 | P11: =M11 -> 207 | S11: Re-Branding Cost | U11: =ROUND(T11/$P$11,-4) -> 0 | V11: 0 | W11: mos
B12: Available Room Nights | D12: =Rooms!S9 -> 75555 | G12: =G10*G11 -> 75555 | J12: =J10*J11 -> 75555 | M12: =M10*M11 -> 75555 | P12: =P10*P11 -> 75555 | S12: Working Capital | T12: =ROUND((($S$54+$S$82)/12)*V12,-6) -> 72000000 | U12: =ROUND(T12/$P$11,-4) -> 350000 | V12: 1 | W12: mos
B13: Occupied Room Nights | D13: =Rooms!S10 -> 65060.15 | G13: =G12*G14 -> 67326.8 | J13: =J12*J14 -> 69593.45 | M13: =M12*M14 -> 71104.55 | P13: =P12*P14 -> 72237.875 | S13: Operator's Tech Fee | U13: =ROUND(T13/$P$11,-4) -> 0
B14: Occupancy | D14: =D13/D12 -> 0.86109656 | F14: 0.03 | G14: =D14+F14 -> 0.89109656 | I14: 0.03 | J14: =G14+I14 -> 0.92109656 | L14: 0.02 | M14: =J14+L14 -> 0.94109656 | O14: 0.015 | P14: =M14+O14 -> 0.95609656 | S14: Total Cost | T14: =SUM(T8:T13) -> 72000000 | U14: =SUM(U8:U13) -> 350000
B15: ADR | D15: =Rooms!S12 -> 10000 | F15: 0.03 | G15: =D15*(1+F15) -> 10300 | I15: 0.03 | J15: =G15*(1+I15) -> 10609 | L15: 0.02 | M15: =J15*(1+L15) -> 10821.18 | O15: 0.02 | P15: =M15*(1+O15) -> 11037.604
B16: RevPar | D16: =D14*D15 -> 8610.9656 | G16: =G14*G15 -> 9178.2945 | J16: =J14*J15 -> 9771.9134 | M16: =M14*M15 -> 10183.775 | P16: =P14*P15 -> 10553.015
B17: No of Hotel Guests | D17: =Rooms!S14 -> 130120.3 | F17: =G17/D17-1 -> 0.034839298 | G17: =G18*G13 -> 134653.6 | I17: =J17/G17-1 -> 0.033666385 | J17: =J18*J13 -> 139186.9 | L17: =M17/J17-1 -> 0.02171325 | M17: =M18*M13 -> 142209.1 | O17: =P17/M17-1 -> 0.015938853 | P17: =P18*P13 -> 144475.75
B18: No of Guest / Occ Room | D18: =D17/D13 -> 2 | G18: =D18 -> 2 | J18: =G18 -> 2 | M18: =J18 -> 2 | P18: =M18 -> 2
B21: Personnel (FT) | D21: =Staffing!C51 -> 20 | G21: =Staffing!E51 -> 20 | J21: =Staffing!G51 -> 20 | M21: =Staffing!I51 -> 20 | P21: =Staffing!K51 -> 20
B22: Personnel (PT) | D22: =Staffing!C52 -> 28 | G22: =Staffing!E52 -> 28 | J22: =Staffing!G52 -> 28 | M22: =Staffing!I52 -> 28 | P22: =Staffing!K52 -> 28
B23: Total Personnel | D23: =SUM(D21:D22) -> 48 | G23: =G21+G22 -> 48 | J23: =J21+J22 -> 48 | M23: =M21+M22 -> 48 | P23: =P21+P22 -> 48
B24: Personnel Costs | D24: =Staffing!D21 -> 189631360 | E24: =D24/D30 -> 0.15297631 | G24: =Staffing!F21 -> 189631360 | H24: =G24/G30 -> 0.14553467 | J24: =Staffing!H21 -> 189631360 | K24: =J24/J30 -> 0.13858199 | M24: =Staffing!J21 -> 189631360 | N24: =M24/M30 -> 0.13418882 | P24: =Staffing!L21 -> 189631360 | Q24: =P24/P30 -> 0.13066072
B26: Revenues | E26: % Rev | F26: % Grth | H26: % Rev | I26: % Grth | K26: % Rev | L26: % Grth | N26: % Rev | O26: % Grth | Q26: % Rev
B27: Rooms | D27: =Rooms!G192 -> 6.506015e+08 | E27: =D27/D$30 -> 0.52484262 | G27: =G13*G15 -> 6.9346604e+08 | H27: =G27/G$30 -> 0.53220813 | J27: =J13*J15 -> 7.3831692e+08 | K27: =J27/J$30 -> 0.53955964 | M27: =M13*M15 -> 7.6943514e+08 | N27: =M27/M$30 -> 0.54447529 | P27: =P13*P15 -> 7.9733303e+08 | Q27: =P27/P$30 -> 0.5493823
B28: Restaurant | D28: =Restaurant!E175 -> 5.6936504e+08 | E28: =D28/D$30 -> 0.45930887 | F28: =F17 -> 0.034839298 | G28: =D28*(1+F28) -> 5.8920132e+08 | H28: =G28/G$30 -> 0.45218902 | I28: =I17 -> 0.033666385 | J28: =G28*(1+I28) -> 6.0903759e+08 | K28: =J28/J$30 -> 0.44508272 | L28: =L17 -> 0.02171325 | M28: =J28*(1+L28) -> 6.2226178e+08 | N28: =M28/M$30 -> 0.44033103 | O28: =O17 -> 0.015938853 | P28: =M28*(1+O28) -> 6.3217992e+08 | Q28: =P28/P$30 -> 0.43558769
B29: MOD | D29: =MOD!E102 -> 19646015 | E29: =D29/D$30 -> 0.015848512 | F29: =F17 -> 0.034839298 | G29: =D29*(1+F29) -> 20330468 | H29: =G29/G$30 -> 0.015602841 | I29: =I17 -> 0.033666385 | J29: =G29*(1+I29) -> 21014922 | K29: =J29/J$30 -> 0.015357638 | L29: =L17 -> 0.02171325 | M29: =J29*(1+L29) -> 21471224 | N29: =M29/M$30 -> 0.01519368 | O29: =O17 -> 0.015938853 | P29: =M29*(1+O29) -> 21813451 | Q29: =P29/P$30 -> 0.01503001
B30: Total | D30: =D27+D28+D29 -> 1.2396126e+09 | E30: =E27+E28+E29 -> 1 | G30: =G27+G28+G29 -> 1.3029978e+09 | H30: =H27+H28+H29 -> 1 | J30: =J27+J28+J29 -> 1.3683694e+09 | K30: =K27+K28+K29 -> 1 | M30: =M27+M28+M29 -> 1.4131681e+09 | N30: =N27+N28+N29 -> 1 | P30: =P27+P28+P29 -> 1.4513264e+09 | Q30: =Q27+Q28+Q29 -> 1
B32: COGS
B33: Rooms | D33: =Rooms!G193 -> 0 | E33: =IFERROR(D33/D27,0) -> 0 | G33: =D33 -> 0 | H33: =IFERROR(G33/G27,0) -> 0 | J33: =G33 -> 0 | K33: =IFERROR(J33/J27,0) -> 0 | M33: =J33 -> 0 | N33: =IFERROR(M33/M27,0) -> 0 | P33: =M33 -> 0 | Q33: =IFERROR(P33/P27,0) -> 0
B34: Restaurant | D34: =Restaurant!E177 -> 1.9927776e+08 | E34: =IFERROR(D34/D28,0) -> 0.35 | F34: =F22 -> 0 | G34: =G28*(E34+F34) -> 2.0622046e+08 | H34: =IFERROR(G34/G28,0) -> 0.35 | I34: =I22 -> 0 | J34: =J28*(H34+I34) -> 2.1316316e+08 | K34: =IFERROR(J34/J28,0) -> 0.35 | L34: =L22 -> 0 | M34: =M28*(K34+L34) -> 2.1779162e+08 | N34: =IFERROR(M34/M28,0) -> 0.35 | O34: =O22 -> 0 | P34: =P28*(N34+O34) -> 2.2126297e+08 | Q34: =IFERROR(P34/P28,0) -> 0.35
B35: MOD | D35: =MOD!E104 -> 9823007.5 | E35: =IFERROR(D35/D29,0) -> 0.5 | F35: =F23 -> 0 | G35: =G29*(E35+F35) -> 10165234 | H35: =IFERROR(G35/G29,0) -> 0.5 | I35: =I23 -> 0 | J35: =J29*(H35+I35) -> 10507461 | K35: =IFERROR(J35/J29,0) -> 0.5 | L35: =L23 -> 0 | M35: =M29*(K35+L35) -> 10735612 | N35: =IFERROR(M35/M29,0) -> 0.5 | O35: =O23 -> 0 | P35: =P29*(N35+O35) -> 10906725 | Q35: =IFERROR(P35/P29,0) -> 0.5
B36: Total | D36: =D33+D34+D35 -> 2.0910077e+08 | E36: =D36/D$30 -> 0.16868236 | G36: =G33+G34+G35 -> 2.1638569e+08 | H36: =G36/G$30 -> 0.16606758 | J36: =J33+J34+J35 -> 2.2367062e+08 | K36: =J36/J$30 -> 0.16345777 | M36: =M33+M34+M35 -> 2.2852724e+08 | N36: =M36/M$30 -> 0.1617127 | P36: =P33+P34+P35 -> 2.321697e+08 | Q36: =P36/P$30 -> 0.1599707
B38: Personnel Expense
B39: Rooms | D39: =Rooms!G169 -> 55306560 | E39: =IFERROR(D39/D27,0) -> 0.085008349 | F39: Dept | G39: =Rooms!H169 -> 55306560 | H39: =IFERROR(G39/G27,0) -> 0.079753811 | I39: Dept | J39: =Rooms!I169 -> 55306560 | K39: =IFERROR(J39/J27,0) -> 0.07490897 | L39: Dept | M39: =Rooms!J169 -> 55306560 | N39: =IFERROR(M39/M27,0) -> 0.071879431 | O39: Dept | P39: =Rooms!K169 -> 55306560 | Q39: =IFERROR(P39/P27,0) -> 0.069364441
B40: Restaurant | D40: =Restaurant!E164 -> 124460800 | E40: =IFERROR(D40/D28,0) -> 0.21859579 | F40: Dept | G40: =Restaurant!F164 -> 124460800 | H40: =IFERROR(G40/G28,0) -> 0.21123646 | I40: Dept | J40: =Restaurant!G164 -> 124460800 | K40: =IFERROR(J40/J28,0) -> 0.20435651 | L40: Dept | M40: =Restaurant!H164 -> 124460800 | N40: =IFERROR(M40/M28,0) -> 0.20001357 | O40: Dept | P40: =Restaurant!I164 -> 124460800 | Q40: =IFERROR(P40/P28,0) -> 0.1968756
B41: MOD | D41: =MOD!E91 -> 0 | E41: =IFERROR(D41/D29,0) -> 0 | F41: Dept | G41: =MOD!F81 -> 0 | H41: =IFERROR(G41/G29,0) -> 0 | I41: Dept | J41: =MOD!G91 -> 0 | K41: =IFERROR(J41/J29,0) -> 0 | L41: Dept | M41: =MOD!H91 -> 0 | N41: =IFERROR(M41/M29,0) -> 0 | O41: Dept | P41: =MOD!I91 -> 0 | Q41: =IFERROR(P41/P29,0) -> 0
B42: Total | D42: =D39+D40+D41 -> 179767360 | E42: =D42/D$30 -> 0.14501899 | G42: =G39+G40+G41 -> 179767360 | H42: =G42/G$30 -> 0.13796444 | J42: =J39+J40+J41 -> 179767360 | K42: =J42/J$30 -> 0.13137341 | M42: =M39+M40+M41 -> 179767360 | N42: =M42/M$30 -> 0.12720875 | P42: =P39+P40+P41 -> 179767360 | Q42: =P42/P$30 -> 0.12386418
B44: Other Expense
B45: Rooms | D45: =Rooms!G195 -> 2.3746955e+08 | E45: =IFERROR(D45/D27,0) -> 0.365 | F45: =F33 -> 0 | G45: =G27*(E45+F45) -> 2.5311511e+08 | H45: =IFERROR(G45/G27,0) -> 0.365 | I45: =I33 -> 0 | J45: =J27*(H45+I45) -> 2.6948567e+08 | K45: =IFERROR(J45/J27,0) -> 0.365 | L45: =L33 -> 0 | M45: =M27*(K45+L45) -> 2.8084382e+08 | N45: =IFERROR(M45/M27,0) -> 0.365 | O45: =O33 -> 0 | P45: =P27*(N45+O45) -> 2.9102656e+08 | Q45: =IFERROR(P45/P27,0) -> 0.365
B46: Restaurant | D46: =Restaurant!E178 -> 28468252 | E46: =IFERROR(D46/D28,0) -> 0.05 | F46: =F34 -> 0 | G46: =G28*(E46+F46) -> 29460066 | H46: =IFERROR(G46/G28,0) -> 0.05 | I46: =I34 -> 0 | J46: =J28*(H46+I46) -> 30451880 | K46: =IFERROR(J46/J28,0) -> 0.05 | L46: =L34 -> 0 | M46: =M28*(K46+L46) -> 31113089 | N46: =IFERROR(M46/M28,0) -> 0.05 | O46: =O34 -> 0 | P46: =P28*(N46+O46) -> 31608996 | Q46: =IFERROR(P46/P28,0) -> 0.05
B47: MOD | D47: =MOD!E105 -> 0 | E47: =IFERROR(D47/D29,0) -> 0 | F47: =F35 -> 0 | G47: =G29*(E47+F47) -> 0 | H47: =IFERROR(G47/G29,0) -> 0 | I47: =I35 -> 0 | J47: =J29*(H47+I47) -> 0 | K47: =IFERROR(J47/J29,0) -> 0 | L47: =L35 -> 0 | M47: =M29*(K47+L47) -> 0 | N47: =IFERROR(M47/M29,0) -> 0 | O47: =O35 -> 0 | P47: =P29*(N47+O47) -> 0 | Q47: =IFERROR(P47/P29,0) -> 0
B48: Total | D48: =D45+D46+D47 -> 2.659378e+08 | E48: =D48/D$30 -> 0.214533 | G48: =G45+G46+G47 -> 2.8257517e+08 | H48: =G48/G$30 -> 0.21686542 | J48: =J45+J46+J47 -> 2.9993755e+08 | K48: =J48/J$30 -> 0.2191934 | M48: =M45+M46+M47 -> 3.1195691e+08 | N48: =M48/M$30 -> 0.22075003 | P48: =P45+P46+P47 -> 3.2263555e+08 | Q48: =P48/P$30 -> 0.22230392
B50: Department Expense
B51: Rooms | D51: =D33+D39+D45 -> 2.9277611e+08 | E51: =IFERROR(D51/D27,0) -> 0.45000835 | G51: =G33+G39+G45 -> 3.0842167e+08 | H51: =IFERROR(G51/G27,0) -> 0.44475381 | J51: =J33+J39+J45 -> 3.2479223e+08 | K51: =IFERROR(J51/J27,0) -> 0.43990897 | M51: =M33+M39+M45 -> 3.3615038e+08 | N51: =IFERROR(M51/M27,0) -> 0.43687943 | P51: =P33+P39+P45 -> 3.4633312e+08 | Q51: =IFERROR(P51/P27,0) -> 0.43436444
B52: Restaurant | D52: =D34+D40+D46 -> 3.5220682e+08 | E52: =IFERROR(D52/D28,0) -> 0.61859579 | G52: =G34+G40+G46 -> 3.6014133e+08 | H52: =IFERROR(G52/G28,0) -> 0.61123646 | J52: =J34+J40+J46 -> 3.6807584e+08 | K52: =IFERROR(J52/J28,0) -> 0.60435651 | M52: =M34+M40+M46 -> 3.7336551e+08 | N52: =IFERROR(M52/M28,0) -> 0.60001357 | P52: =P34+P40+P46 -> 3.7733277e+08 | Q52: =IFERROR(P52/P28,0) -> 0.5968756
B53: MOD | D53: =D35+D41+D47 -> 9823007.5 | E53: =IFERROR(D53/D29,0) -> 0.5 | G53: =G35+G41+G47 -> 10165234 | H53: =IFERROR(G53/G29,0) -> 0.5 | J53: =J35+J41+J47 -> 10507461 | K53: =IFERROR(J53/J29,0) -> 0.5 | M53: =M35+M41+M47 -> 10735612 | N53: =IFERROR(M53/M29,0) -> 0.5 | P53: =P35+P41+P47 -> 10906725 | Q53: =IFERROR(P53/P29,0) -> 0.5
B54: Total | D54: =D51+D52+D53 -> 6.5480593e+08 | E54: =D54/D$30 -> 0.52823435 | G54: =G51+G52+G53 -> 6.7872823e+08 | H54: =G54/G$30 -> 0.52089743 | J54: =J51+J52+J53 -> 7.0337553e+08 | K54: =J54/J$30 -> 0.51402459 | M54: =M51+M52+M53 -> 7.2025151e+08 | N54: =M54/M$30 -> 0.50967149 | P54: =P51+P52+P53 -> 7.3457261e+08 | Q54: =P54/P$30 -> 0.5061388 | S54: =D54 -> 6.5480593e+08 | T54: Depart Exp Year 1
B56: Department Profit
B57: Rooms | D57: =D27-D51 -> 3.578254e+08 | E57: =IFERROR(D57/D27,0) -> 0.54999165 | G57: =G27-G51 -> 3.8504438e+08 | H57: =IFERROR(G57/G27,0) -> 0.55524619 | J57: =J27-J51 -> 4.1352468e+08 | K57: =IFERROR(J57/J27,0) -> 0.56009103 | M57: =M27-M51 -> 4.3328475e+08 | N57: =IFERROR(M57/M27,0) -> 0.56312057 | P57: =P27-P51 -> 4.5099992e+08 | Q57: =IFERROR(P57/P27,0) -> 0.56563556
B58: Restaurant | D58: =D28-D52 -> 2.1715822e+08 | E58: =IFERROR(D58/D28,0) -> 0.38140421 | G58: =G28-G52 -> 2.2905999e+08 | H58: =IFERROR(G58/G28,0) -> 0.38876354 | J58: =J28-J52 -> 2.4096176e+08 | K58: =IFERROR(J58/J28,0) -> 0.39564349 | M58: =M28-M52 -> 2.4889627e+08 | N58: =IFERROR(M58/M28,0) -> 0.39998643 | P58: =P28-P52 -> 2.5484715e+08 | Q58: =IFERROR(P58/P28,0) -> 0.4031244
B59: MOD | D59: =D29-D53 -> 9823007.5 | E59: =IFERROR(D59/D29,0) -> 0.5 | G59: =G29-G53 -> 10165234 | H59: =IFERROR(G59/G29,0) -> 0.5 | J59: =J29-J53 -> 10507461 | K59: =IFERROR(J59/J29,0) -> 0.5 | M59: =M29-M53 -> 10735612 | N59: =IFERROR(M59/M29,0) -> 0.5 | P59: =P29-P53 -> 10906725 | Q59: =IFERROR(P59/P29,0) -> 0.5
B60: Total | D60: =D57+D58+D59 -> 5.8480663e+08 | E60: =D60/D$30 -> 0.47176565 | G60: =G57+G58+G59 -> 6.242696e+08 | H60: =G60/G$30 -> 0.47910257 | J60: =J57+J58+J59 -> 6.649939e+08 | K60: =J60/J$30 -> 0.48597541 | M60: =M57+M58+M59 -> 6.9291663e+08 | N60: =M60/M$30 -> 0.49032851 | P60: =P57+P58+P59 -> 7.1675379e+08 | Q60: =P60/P$30 -> 0.4938612
B62: Undistributable Expense
B63: Administration and General | D63: =D64+D65 -> 52497283 | E63: =D63/D$30 -> 0.042349751 | G63: =G64+G65 -> 52497283 | H63: =G63/G$30 -> 0.040289616 | J63: =J64+J65 -> 52497283 | K63: =J63/J$30 -> 0.038364846 | M63: =M64+M65 -> 52923615 | N63: =M63/M$30 -> 0.037450331 | P63: =P64+P65 -> 53354212 | Q63: =P63/P$30 -> 0.036762379
B64: Personnel | D64: ='Undist Expense'!F182 -> 9864000 | E64: =D64/D$30 -> 0.007957325 | F64: Dept | G64: ='Undist Expense'!H182 -> 9864000 | H64: =G64/G$30 -> 0.0075702352 | I64: Dept | J64: ='Undist Expense'!J182 -> 9864000 | K64: =J64/J$30 -> 0.0072085796 | L64: Dept | M64: ='Undist Expense'!L182 -> 9864000 | N64: =M64/M$30 -> 0.0069800611 | O64: Dept | P64: ='Undist Expense'!N182 -> 9864000 | Q64: =P64/P$30 -> 0.0067965414
B65: Other | D65: ='Undist Expense'!E157 -> 42633283 | E65: =D65/D$30 -> 0.034392426 | F65: 0 | G65: =D65*(1+F65) -> 42633283 | H65: =G65/G$30 -> 0.032719381 | I65: 0 | J65: =G65*(1+I65) -> 42633283 | K65: =J65/J$30 -> 0.031156266 | L65: 0.01 | M65: =J65*(1+L65) -> 43059615 | N65: =M65/M$30 -> 0.03047027 | O65: 0.01 | P65: =M65*(1+O65) -> 43490212 | Q65: =P65/P$30 -> 0.029965838
B66: Sales and Marketing | D66: =D67+D68 -> 30792251 | E66: =D66/D$30 -> 0.024840222 | G66: =G67+G68 -> 32059957 | H66: =G66/G$30 -> 0.024604766 | J66: =J67+J68 -> 33367389 | K66: =J66/J$30 -> 0.024384781 | M66: =M67+M68 -> 34263363 | N66: =M66/M$30 -> 0.024245779 | P66: =P67+P68 -> 35026528 | Q66: =P66/P$30 -> 0.024134149
B67: Personnel | D67: ='Undist Expense'!F183 -> 0 | E67: =D67/D$30 -> 0 | F67: Dept | G67: ='Undist Expense'!H183 -> 0 | H67: =G67/G$30 -> 0 | I67: Dept | J67: ='Undist Expense'!J183 -> 0 | K67: =J67/J$30 -> 0 | L67: Dept | M67: ='Undist Expense'!L183 -> 0 | N67: =M67/M$30 -> 0 | O67: Dept | P67: ='Undist Expense'!N183 -> 0 | Q67: =P67/P$30 -> 0
B68: Other | D68: ='Undist Expense'!E161 -> 30792251 | E68: =D68/D$30 -> 0.024840222 | F68: below | G68: =SUM(G118:G120)*G30+G121 -> 32059957 | H68: =G68/G$30 -> 0.024604766 | I68: below | J68: =SUM(J118:J120)*J30+J121 -> 33367389 | K68: =J68/J$30 -> 0.024384781 | L68: below | M68: =SUM(M118:M120)*M30+M121 -> 34263363 | N68: =M68/M$30 -> 0.024245779 | O68: below | P68: =SUM(P118:P120)*P30+P121 -> 35026528 | Q68: =P68/P$30 -> 0.024134149
B69: Maintenance / Engineer | D69: =D70+D71 -> 27596126 | E69: =D69/D$30 -> 0.022261896 | G69: =G70+G71 -> 27596126 | H69: =G69/G$30 -> 0.02117895 | J69: =J70+J71 -> 27596126 | K69: =J69/J$30 -> 0.02016716 | M69: =M70+M71 -> 27872087 | N69: =M69/M$30 -> 0.019723121 | P69: =P70+P71 -> 28150808 | Q69: =P69/P$30 -> 0.019396607
B70: Personnel | D70: ='Undist Expense'!F184 -> 0 | E70: =D70/D$30 -> 0 | F70: Dept | G70: ='Undist Expense'!H184 -> 0 | H70: =G70/G$30 -> 0 | I70: Dept | J70: ='Undist Expense'!J184 -> 0 | K70: =J70/J$30 -> 0 | L70: Dept | M70: ='Undist Expense'!L184 -> 0 | N70: =M70/M$30 -> 0 | O70: Dept | P70: ='Undist Expense'!N184 -> 0 | Q70: =P70/P$30 -> 0
B71: Other | D71: ='Undist Expense'!E165 -> 27596126 | E71: =D71/D$30 -> 0.022261896 | F71: 0 | G71: =D71*(1+F71) -> 27596126 | H71: =G71/G$30 -> 0.02117895 | I71: 0 | J71: =G71*(1+I71) -> 27596126 | K71: =J71/J$30 -> 0.02016716 | L71: 0.01 | M71: =J71*(1+L71) -> 27872087 | N71: =M71/M$30 -> 0.019723121 | O71: 0.01 | P71: =M71*(1+O71) -> 28150808 | Q71: =P71/P$30 -> 0.019396607
B72: Utilities | D72: ='Undist Expense'!E167 -> 97590226 | E72: =D72/D$30 -> 0.078726393 | G72: =G135*G13 -> 1.009902e+08 | H72: =G72/G$30 -> 0.077506039 | J72: =J135*J13 -> 1.0439018e+08 | K72: =J72/J$30 -> 0.076288006 | M72: =M135*M13 -> 1.0665683e+08 | N72: =M72/M$30 -> 0.075473556 | P72: =P135*P13 -> 1.0835681e+08 | Q72: =P72/P$30 -> 0.07466054
B74: Annual Fees | D74: =SUM(D75:D80) -> 0 | E74: =D74/D$30 -> 0 | G74: =SUM(G75:G80) -> 0 | H74: =G74/G$30 -> 0 | J74: =SUM(J75:J80) -> 0 | K74: =J74/J$30 -> 0 | M74: =SUM(M75:M80) -> 0 | N74: =M74/M$30 -> 0 | P74: =SUM(P75:P80) -> 0 | Q74: =P74/P$30 -> 0
B75: xx fee | D75: =D$27*$S75 -> 0 | E75: =D75/D$30 -> 0 | G75: =G$27*$S75 -> 0 | H75: =G75/G$30 -> 0 | J75: =J$27*$S75 -> 0 | K75: =J75/J$30 -> 0 | M75: =M$27*$S75 -> 0 | N75: =M75/M$30 -> 0 | P75: =P$27*$S75 -> 0 | Q75: =P75/P$30 -> 0
B76: yy fee | D76: =D$30*$S76 -> 0 | E76: =D76/D$30 -> 0 | G76: =G$30*$S76 -> 0 | H76: =G76/G$30 -> 0 | J76: =J$30*$S76 -> 0 | K76: =J76/J$30 -> 0 | M76: =M$30*$S76 -> 0 | N76: =M76/M$30 -> 0 | P76: =P$30*$S76 -> 0 | Q76: =P76/P$30 -> 0
B77: zz fee | D77: =D$27*$S77 -> 0 | E77: =D77/D$30 -> 0 | G77: =G$27*$S77 -> 0 | H77: =G77/G$30 -> 0 | J77: =J$27*$S77 -> 0 | K77: =J77/J$30 -> 0 | M77: =M$27*$S77 -> 0 | N77: =M77/M$30 -> 0 | P77: =P$27*$S77 -> 0 | Q77: =P77/P$30 -> 0
D78: =$S78 -> 0 | E78: =D78/D$30 -> 0 | G78: =$S78 -> 0 | H78: =G78/G$30 -> 0 | J78: =$S78 -> 0 | K78: =J78/J$30 -> 0 | M78: =$S78 -> 0 | N78: =M78/M$30 -> 0 | P78: =$S78 -> 0 | Q78: =P78/P$30 -> 0
D79: =$S79 -> 0 | E79: =D79/D$30 -> 0 | G79: =$S79 -> 0 | H79: =G79/G$30 -> 0 | J79: =$S79 -> 0 | K79: =J79/J$30 -> 0 | M79: =$S79 -> 0 | N79: =M79/M$30 -> 0 | P79: =$S79 -> 0 | Q79: =P79/P$30 -> 0
D80: =D30*$S80*$U80 -> 0 | E80: =D80/D$30 -> 0 | G80: =G30*$S80*$U80 -> 0 | H80: =G80/G$30 -> 0 | J80: =J30*$S80*$U80 -> 0 | K80: =J80/J$30 -> 0 | M80: =M30*$S80*$U80 -> 0 | N80: =M80/M$30 -> 0 | P80: =P30*$S80*$U80 -> 0 | Q80: =P80/P$30 -> 0
B82: Total | D82: =D63+D66+D69+D72+D74 -> 2.0847588e+08 | E82: =D82/D$30 -> 0.16817826 | G82: =G63+G66+G69+G72+G74 -> 2.1314357e+08 | H82: =G82/G$30 -> 0.16357937 | J82: =J63+J66+J69+J72+J74 -> 2.1785097e+08 | K82: =J82/J$30 -> 0.15920479 | M82: =M63+M66+M69+M72+M74 -> 2.2171589e+08 | N82: =M82/M$30 -> 0.15689279 | P82: =P63+P66+P69+P72+P74 -> 2.2488836e+08 | Q82: =P82/P$30 -> 0.15495368 | S82: =D82 -> 2.0847588e+08 | T82: Undist Exp Year 1
B84: House Profit | D84: =D60-D82 -> 3.7633074e+08 | E84: =D84/D$30 -> 0.30358739 | G84: =G60-G82 -> 4.1112604e+08 | H84: =G84/G$30 -> 0.31552319 | J84: =J60-J82 -> 4.4714293e+08 | K84: =J84/J$30 -> 0.32677062 | M84: =M60-M82 -> 4.7120074e+08 | N84: =M84/M$30 -> 0.33343572 | P84: =P60-P82 -> 4.9186543e+08 | Q84: =P84/P$30 -> 0.33890752
B87: Base Management Fee | D87: =$R$87*D30 -> 24792251 | E87: =D87/D$30 -> 0.02 | G87: =$R$87*G30 -> 26059957 | H87: =G87/G$30 -> 0.02 | J87: =$R$87*J30 -> 27367389 | K87: =J87/J$30 -> 0.02 | M87: =$R$87*M30 -> 28263363 | N87: =M87/M$30 -> 0.02 | P87: =$R$87*P30 -> 29026528 | Q87: =P87/P$30 -> 0.02 | R87: 0.02 | S87: of GOR
B89: Gross Operating Profit | D89: =D84-D87 -> 3.5153849e+08 | E89: =D89/D$30 -> 0.28358739 | G89: =G84-G87 -> 3.8506608e+08 | H89: =G89/G$30 -> 0.29552319 | J89: =J84-J87 -> 4.1977554e+08 | K89: =J89/J$30 -> 0.30677062 | M89: =M84-M87 -> 4.4293738e+08 | N89: =M89/M$30 -> 0.31343572 | P89: =P84-P87 -> 4.6283891e+08 | Q89: =P89/P$30 -> 0.31890752
T90: =INT(8) -> 8
B92: Incentive Fee | D92: =IF(D89<0,0,$R$92*D89) -> 28123079 | E92: =D92/D$30 -> 0.022686991 | G92: =IF(G89<0,0,$R$92*G89) -> 30805286 | H92: =G92/G$30 -> 0.023641856 | J92: =IF(J89<0,0,$R$92*J89) -> 33582043 | K92: =J92/J$30 -> 0.02454165 | M92: =IF(M89<0,0,$R$92*M89) -> 35434990 | N92: =M92/M$30 -> 0.025074858 | P92: =IF(P89<0,0,$R$92*P89) -> 37027112 | Q92: =P92/P$30 -> 0.025512602 | R92: 0.08 | S92: of GOP
B94: Owner's Expense
B95: Property Tax | D95: 12000000 | E95: =D95/D$30 -> 0.009680444 | G95: =D95 -> 12000000 | H95: =G95/G$30 -> 0.0092095318 | J95: =G95 -> 12000000 | K95: =J95/J$30 -> 0.0087695616 | M95: =J95 -> 12000000 | N95: =M95/M$30 -> 0.0084915585 | P95: =M95 -> 12000000 | Q95: =P95/P$30 -> 0.0082682985
B96: Property Insurance | D96: =R96*D11 -> 2070000 | E96: =D96/D$30 -> 0.0016698766 | G96: =D96 -> 2070000 | H96: =G96/G$30 -> 0.0015886442 | J96: =G96 -> 2070000 | K96: =J96/J$30 -> 0.0015127494 | M96: =J96 -> 2070000 | N96: =M96/M$30 -> 0.0014647938 | P96: =M96 -> 2070000 | Q96: =P96/P$30 -> 0.0014262815 | R96: 10000 | S96: per room
B97: FF&E Reserve | D97: =IF(D30*$R$97 <50000000,D30*$R$97,50000000) -> 37188377 | E97: =D97/D$30 -> 0.03 | G97: =IF(G30*$R$97 <50000000,G30*$R$97,50000000) -> 39089935 | H97: =G97/G$30 -> 0.03 | J97: =IF(J30*$R$97 <50000000,J30*$R$97,50000000) -> 41051083 | K97: =J97/J$30 -> 0.03 | M97: =IF(M30*$R$97 <50000000,M30*$R$97,50000000) -> 42395044 | N97: =M97/M$30 -> 0.03 | P97: =IF(P30*$R$97 <50000000,P30*$R$97,50000000) -> 43539792 | Q97: =P97/P$30 -> 0.03 | R97: 0.03 | S97: of GOR, capped at 50M, notional
B98: Capex Reserve | D98: =D30*$R$98 -> 0 | E98: =D98/D$30 -> 0 | G98: =G30*$R$98 -> 0 | H98: =G98/G$30 -> 0 | J98: =J30*$R$98 -> 0 | K98: =J98/J$30 -> 0 | M98: =M30*$R$98 -> 0 | N98: =M98/M$30 -> 0 | P98: =P30*$R$98 -> 0 | Q98: =P98/P$30 -> 0 | R98: 0 | S98: of GOR
B99: Total | D99: =SUM(D95:D98) -> 51258377 | E99: =D99/D$30 -> 0.041350321 | G99: =SUM(G95:G98) -> 53159935 | H99: =G99/G$30 -> 0.040798176 | J99: =SUM(J95:J98) -> 55121083 | K99: =J99/J$30 -> 0.040282311 | M99: =SUM(M95:M98) -> 56465044 | N99: =M99/M$30 -> 0.039956352 | P99: =SUM(P95:P98) -> 57609792 | Q99: =P99/P$30 -> 0.03969458
B101: Property NOI | D101: =D89-D92-D95-D96 -> 3.0934541e+08 | E101: =D101/D$30 -> 0.24955008 | G101: =G89-G92-G95-G96 -> 3.4019079e+08 | H101: =G101/G$30 -> 0.26108316 | J101: =J89-J92-J95-J96 -> 3.721235e+08 | K101: =J101/J$30 -> 0.27194666 | M101: =M89-M92-M95-M96 -> 3.9343239e+08 | N101: =M101/M$30 -> 0.27840451 | P101: =P89-P92-P95-P96 -> 4.1174179e+08 | Q101: =P101/P$30 -> 0.28370034
B104: Property NCF | D104: =D101-D97-D98 -> 2.7215703e+08 | E104: =D104/D$30 -> 0.21955008 | G104: =G101-G97-G98 -> 3.0110086e+08 | H104: =G104/G$30 -> 0.23108316 | J104: =J101-J97-J98 -> 3.3107241e+08 | K104: =J104/J$30 -> 0.24194666 | M104: =M101-M97-M98 -> 3.5103735e+08 | N104: =M104/M$30 -> 0.24840451 | P104: =P101-P97-P98 -> 3.68202e+08 | Q104: =P104/P$30 -> 0.25370034
B107: NOI Yield to Purchase Price | D107: =D101/$T$8 -> #DIV/0! | G107: =G101/$T$8 -> #DIV/0! | J107: =J101/$T$8 -> #DIV/0! | M107: =M101/$T$8 -> #DIV/0! | P107: =P101/$T$8 -> #DIV/0!
B108: NOI Yield to Total Cost | D108: =D101/$T$14 -> 4.296464 | G108: =G101/$T$14 -> 4.7248721 | J108: =J101/$T$14 -> 5.1683819 | M108: =M101/$T$14 -> 5.4643388 | P108: =P101/$T$14 -> 5.718636
B110: NCF Yield to Purchase Price | D110: =D104/$T$8 -> #DIV/0! | G110: =G104/$T$8 -> #DIV/0! | J110: =J104/$T$8 -> #DIV/0! | M110: =M104/$T$8 -> #DIV/0! | P110: =P104/$T$8 -> #DIV/0!
B111: NCF Yield to Total Cost | D111: =D104/$T$14 -> 3.7799588 | G111: =G104/$T$14 -> 4.1819564 | J111: =J104/$T$14 -> 4.598228 | M111: =M104/$T$14 -> 4.8755187 | P111: =P104/$T$14 -> 5.1139167
B117: Sales and Marketing - Other | D117: =D68/D30 -> 0.024840222 | G117: =G68/G30 -> 0.024604766 | J117: =J68/J30 -> 0.024384781 | M117: =M68/M30 -> 0.024245779 | P117: =P68/P30 -> 0.024134149
B118: 広告宣伝費 x GOR | D118: ='Undist Expense'!H137 -> 0.005 | G118: =D118 -> 0.005 | J118: =G118 -> 0.005 | M118: =J118 -> 0.005 | P118: =M118 -> 0.005
B119: S&Mフィー x GOR | D119: ='Undist Expense'!H138 -> 0.01 | G119: 0.01 | J119: 0.01 | M119: 0.01 | P119: 0.01
B120: その他 x GOR | D120: ='Undist Expense'!H139 -> 0.005 | G120: =D120 -> 0.005 | J120: =G120 -> 0.005 | M120: =J120 -> 0.005 | P120: =M120 -> 0.005
B121: HMJO委託料 | D121: ='Undist Expense'!E140 -> 6000000 | G121: =D121 -> 6000000 | J121: =G121 -> 6000000 | M121: =J121 -> 6000000 | P121: =M121 -> 6000000
B123: Rooms / Occ Room Night (JPY) | D123: JPY | E123: % Rev | G123: JPY | H123: % Rev | J123: JPY | K123: % Rev | M123: JPY | N123: % Rev | P123: JPY | Q123: % Rev
B124: Revenues | D124: =D27/D$13 -> 10000 | G124: =G27/G$13 -> 10300 | J124: =J27/J$13 -> 10609 | M124: =M27/M$13 -> 10821.18 | P124: =P27/P$13 -> 11037.604
B125: COGS | D125: =D33/D$13 -> 0 | E125: =D125/D$124 -> 0 | G125: =G33/G$13 -> 0 | H125: =G125/G$124 -> 0 | J125: =J33/J$13 -> 0 | K125: =J125/J$124 -> 0 | M125: =M33/M$13 -> 0 | N125: =M125/M$124 -> 0 | P125: =P33/P$13 -> 0 | Q125: =P125/P$124 -> 0
B126: Personnel | D126: =D39/D$13 -> 850.08349 | E126: =D126/D$124 -> 0.085008349 | G126: =G39/G$13 -> 821.46426 | H126: =G126/G$124 -> 0.079753811 | J126: =J39/J$13 -> 794.70927 | K126: =J126/J$124 -> 0.07490897 | M126: =M39/M$13 -> 777.82026 | N126: =M126/M$124 -> 0.071879431 | P126: =P39/P$13 -> 765.6172 | Q126: =P126/P$124 -> 0.069364441
B127: Other | D127: =D45/D$13 -> 3650 | E127: =D127/D$124 -> 0.365 | G127: =G45/G$13 -> 3759.5 | H127: =G127/G$124 -> 0.365 | J127: =J45/J$13 -> 3872.285 | K127: =J127/J$124 -> 0.365 | M127: =M45/M$13 -> 3949.7307 | N127: =M127/M$124 -> 0.365 | P127: =P45/P$13 -> 4028.7253 | Q127: =P127/P$124 -> 0.365
B128: Total Costs | D128: =SUM(D125:D127) -> 4500.0835 | E128: =D128/D$124 -> 0.45000835 | G128: =SUM(G125:G127) -> 4580.9642 | H128: =G128/G$124 -> 0.44475381 | J128: =SUM(J125:J127) -> 4666.9943 | K128: =J128/J$124 -> 0.43990897 | M128: =SUM(M125:M127) -> 4727.551 | N128: =M128/M$124 -> 0.43687943 | P128: =SUM(P125:P127) -> 4794.3425 | Q128: =P128/P$124 -> 0.43436444
B129: Department Profit | D129: =D124-D128 -> 5499.9165 | E129: =D129/D$124 -> 0.54999165 | G129: =G124-G128 -> 5719.0358 | H129: =G129/G$124 -> 0.55524619 | J129: =J124-J128 -> 5942.0057 | K129: =J129/J$124 -> 0.56009103 | M129: =M124-M128 -> 6093.629 | N129: =M129/M$124 -> 0.56312057 | P129: =P124-P128 -> 6243.2611 | Q129: =P129/P$124 -> 0.56563556
B131: Undist Exp / Occ Room Night (JPY) | D131: JPY | E131: % Rev | G131: JPY | H131: % Rev | J131: JPY | K131: % Rev | M131: JPY | N131: % Rev | P131: JPY | Q131: % Rev
B132: Administration and General | D132: =D63/D$13 -> 806.9038 | E132: =E63 -> 0.042349751 | G132: =G63/G$13 -> 779.73826 | H132: =H63 -> 0.040289616 | J132: =J63/J$13 -> 754.34229 | K132: =K63 -> 0.038364846 | M132: =M63/M$13 -> 744.30701 | N132: =N63 -> 0.037450331 | P132: =P63/P$13 -> 738.59054 | Q132: =Q63 -> 0.036762379
...

Sheet Rooms
A1: ='Room Types'!$A$1 -> Hotel xxxx | G1: Year 1
A2: Room Revenues | D2: No of Rooms | E2: =E30 -> 207
A3: JPY
G5: Month
C6: Year 1 | G6: 1 | H6: =G6+1 -> 2 | I6: =H6+1 -> 3 | J6: =I6+1 -> 4 | K6: =J6+1 -> 5 | L6: =K6+1 -> 6 | M6: =L6+1 -> 7 | N6: =M6+1 -> 8 | O6: =N6+1 -> 9 | ... R6: =Q6+1 -> 12 | S6: Total
C7: No of Days (all) | G7: 31 | H7: 28 | I7: 31 | J7: 30 | K7: 31 | L7: 30 | M7: 31 | N7: 31 | O7: 30 | P7: 31 | Q7: 30 | R7: 31 | S7: =SUM(G7:R7) -> 365
C8: Number of Rooms | G8: =E30 -> 207 | H8: =G8 -> 207 | I8: =H8 -> 207 | J8: =I8 -> 207 | K8: =J8 -> 207 | L8: =K8 -> 207 | M8: =L8 -> 207 | N8: =M8 -> 207 | O8: =N8 -> 207 | ... R8: =Q8 -> 207 | S8: =SUM(G8:R8) -> 2484
C9: Available Room Nights | G9: =G7*G8 -> 6417 | H9: =H7*H8 -> 5796 | I9: =I7*I8 -> 6417 | J9: =J7*J8 -> 6210 | K9: =K7*K8 -> 6417 | L9: =L7*L8 -> 6210 | M9: =M7*M8 -> 6417 | N9: =N7*N8 -> 6417 | ... R9: =R7*R8 -> 6417 | S9: =SUM(G9:R9) -> 75555
C10: Occupied Room Nights | G10: =G30 -> 5133.6 | H10: =H30 -> 4876.5554 | I10: =I30 -> 5199.7493 | J10: =J30 -> 4419.7608 | K10: =K30 -> 5652.8978 | L10: =L30 -> 5785.9776 | M10: =M30 -> 5873.7426 | N10: =N30 -> 5879.9929 | ... R10: =R30 -> 5475.024 | S10: =SUM(G10:R10) -> 65060.15
C11: Occupancy | G11: =G10/G9 -> 0.8 | H11: =H10/H9 -> 0.84136567 | I11: =I10/I9 -> 0.81030844 | J11: =J10/J9 -> 0.71171672 | K11: =K10/K9 -> 0.88092532 | L11: =L10/L9 -> 0.93171943 | M11: =M10/M9 -> 0.91534091 | N11: =N10/N9 -> 0.91631494 | ... S11: =S10/S9 -> 0.86109656
C12: ADR | G12: =G63 -> 10000 | H12: =H63 -> 10000 | I12: =I63 -> 10000 | J12: =J63 -> 10000 | K12: =K63 -> 10000 | L12: =L63 -> 10000 | M12: =M63 -> 10000 | N12: =N63 -> 10000 | ... S12: =S63 -> 10000
C13: RevPar | G13: =G11*G12 -> 8000 | H13: =H11*H12 -> 8413.6567 | I13: =I11*I12 -> 8103.0844 | J13: =J11*J12 -> 7117.1672 | K13: =K11*K12 -> 8809.2532 | L13: =L11*L12 -> 9317.1943 | M13: =M11*M12 -> 9153.4091 | N13: =N11*N12 -> 9163.1494 | ... S13: =S11*S12 -> 8610.9656
C14: Total Guest Count | E14: 2 | G14: =$E$14*G10 -> 10267.2 | H14: =$E$14*H10 -> 9753.1108 | I14: =$E$14*I10 -> 10399.499 | J14: =$E$14*J10 -> 8839.5217 | K14: =$E$14*K10 -> 11305.796 | L14: =$E$14*L10 -> 11571.955 | M14: =$E$14*M10 -> 11747.485 | N14: =$E$14*N10 -> 11759.986 | ... R14: =$E$14*R10 -> 10950.048 | S14: =SUM(G14:R14) -> 130120.3
C15: No of Guests per Day | G15: =G14/G7 -> 331.2 | H15: =H14/H7 -> 348.32539 | I15: =I14/I7 -> 335.46769 | J15: =J14/J7 -> 294.65072 | K15: =K14/K7 -> 364.70308 | L15: =L14/L7 -> 385.73184 | M15: =M14/M7 -> 378.95114 | N15: =N14/N7 -> 379.35438 | ... S15: =S14/S7 -> 356.49397
C18: Room Nights
C19: Type | D19: Size (sqm) | E19: Rooms
B20: 1 | C20: ='Room Types'!C7 -> King | D20: ='Room Types'!H7 -> 27 | E20: ='Room Types'!D7 -> 100 | G20: =G$7*G35*$E20 -> 2480 | H20: =H$7*H35*$E20 -> 2355.8239 | I20: =I$7*I35*$E20 -> 2511.9562 | J20: =J$7*J35*$E20 -> 2135.1502 | K20: =K$7*K35*$E20 -> 2730.8685 | L20: =L$7*L35*$E20 -> 2795.1583 | M20: =M$7*M35*$E20 -> 2837.5568 | N20: =N$7*N35*$E20 -> 2840.5763 | ... R20: =R$7*R35*$E20 -> 2644.9391 | S20: =SUM(G20:R20) -> 31430.024 | T20: =S20/($S$7*E20) -> 0.86109656
B21: =B20+1 -> 2 | C21: ='Room Types'!C8 -> 0 | D21: ='Room Types'!H8 -> 0 | E21: ='Room Types'!D8 -> 0 | G21: =G$7*G36*$E21 -> 0 | H21: =H$7*H36*$E21 -> 0 | I21: =I$7*I36*$E21 -> 0 | J21: =J$7*J36*$E21 -> 0 | K21: =K$7*K36*$E21 -> 0 | L21: =L$7*L36*$E21 -> 0 | M21: =M$7*M36*$E21 -> 0 | N21: =N$7*N36*$E21 -> 0 | ... R21: =R$7*R36*$E21 -> 0 | S21: =SUM(G21:R21) -> 0 | T21: =S21/($S$7*E21) -> #DIV/0!
B22: =B21+1 -> 3 | C22: ='Room Types'!C9 -> Double Double | D22: ='Room Types'!H9 -> 28.3 | E22: ='Room Types'!D9 -> 100 | G22: =G$7*G37*$E22 -> 2480 | H22: =H$7*H37*$E22 -> 2355.8239 | I22: =I$7*I37*$E22 -> 2511.9562 | J22: =J$7*J37*$E22 -> 2135.1502 | K22: =K$7*K37*$E22 -> 2730.8685 | L22: =L$7*L37*$E22 -> 2795.1583 | M22: =M$7*M37*$E22 -> 2837.5568 | N22: =N$7*N37*$E22 -> 2840.5763 | ... R22: =R$7*R37*$E22 -> 2644.9391 | S22: =SUM(G22:R22) -> 31430.024 | T22: =S22/($S$7*E22) -> 0.86109656
B23: =B22+1 -> 4 | C23: ='Room Types'!C10 -> 0 | D23: ='Room Types'!H10 -> 0 | E23: ='Room Types'!D10 -> 0 | G23: =G$7*G38*$E23 -> 0 | H23: =H$7*H38*$E23 -> 0 | I23: =I$7*I38*$E23 -> 0 | J23: =J$7*J38*$E23 -> 0 | K23: =K$7*K38*$E23 -> 0 | L23: =L$7*L38*$E23 -> 0 | M23: =M$7*M38*$E23 -> 0 | N23: =N$7*N38*$E23 -> 0 | ... R23: =R$7*R38*$E23 -> 0 | S23: =SUM(G23:R23) -> 0 | T23: =S23/($S$7*E23) -> #DIV/0!
B24: =B23+1 -> 5 | C24: ='Room Types'!C11 -> 0 | D24: ='Room Types'!H11 -> 0 | E24: ='Room Types'!D11 -> 0 | G24: =G$7*G39*$E24 -> 0 | H24: =H$7*H39*$E24 -> 0 | I24: =I$7*I39*$E24 -> 0 | J24: =J$7*J39*$E24 -> 0 | K24: =K$7*K39*$E24 -> 0 | L24: =L$7*L39*$E24 -> 0 | M24: =M$7*M39*$E24 -> 0 | N24: =N$7*N39*$E24 -> 0 | ... R24: =R$7*R39*$E24 -> 0 | S24: =SUM(G24:R24) -> 0 | T24: =S24/($S$7*E24) -> #DIV/0!
B25: =B24+1 -> 6 | C25: ='Room Types'!C12 -> 0 | D25: ='Room Types'!H12 -> 0 | E25: ='Room Types'!D12 -> 0 | G25: =G$7*G40*$E25 -> 0 | H25: =H$7*H40*$E25 -> 0 | I25: =I$7*I40*$E25 -> 0 | J25: =J$7*J40*$E25 -> 0 | K25: =K$7*K40*$E25 -> 0 | L25: =L$7*L40*$E25 -> 0 | M25: =M$7*M40*$E25 -> 0 | N25: =N$7*N40*$E25 -> 0 | ... R25: =R$7*R40*$E25 -> 0 | S25: =SUM(G25:R25) -> 0 | T25: =S25/($S$7*E25) -> #DIV/0!
B26: =B25+1 -> 7 | C26: ='Room Types'!C13 -> Junior Suite | D26: ='Room Types'!H13 -> 54 | E26: ='Room Types'!D13 -> 5 | G26: =G$7*G41*$E26 -> 124 | H26: =H$7*H41*$E26 -> 117.79119 | I26: =I$7*I41*$E26 -> 125.59781 | J26: =J$7*J41*$E26 -> 106.75751 | K26: =K$7*K41*$E26 -> 136.54343 | L26: =L$7*L41*$E26 -> 139.75791 | M26: =M$7*M41*$E26 -> 141.87784 | N26: =N$7*N41*$E26 -> 142.02881 | ... R26: =R$7*R41*$E26 -> 132.24696 | S26: =SUM(G26:R26) -> 1571.5012 | T26: =S26/($S$7*E26) -> 0.86109656
B27: =B26+1 -> 8 | C27: ='Room Types'!C14 -> Family Suite | D27: ='Room Types'!H14 -> 56.6 | E27: ='Room Types'!D14 -> 1 | G27: =G$7*G42*$E27 -> 24.8 | H27: =H$7*H42*$E27 -> 23.558239 | I27: =I$7*I42*$E27 -> 25.119562 | J27: =J$7*J42*$E27 -> 21.351502 | K27: =K$7*K42*$E27 -> 27.308685 | L27: =L$7*L42*$E27 -> 27.951583 | M27: =M$7*M42*$E27 -> 28.375568 | N27: =N$7*N42*$E27 -> 28.405763 | ... R27: =R$7*R42*$E27 -> 26.449391 | S27: =SUM(G27:R27) -> 314.30024 | T27: =S27/($S$7*E27) -> 0.86109656
B28: =B27+1 -> 9 | C28: ='Room Types'!C15 -> Exec. Suite | D28: ='Room Types'!H15 -> 81 | E28: ='Room Types'!D15 -> 1 | G28: =G$7*G43*$E28 -> 24.8 | H28: =H$7*H43*$E28 -> 23.558239 | I28: =I$7*I43*$E28 -> 25.119562 | J28: =J$7*J43*$E28 -> 21.351502 | K28: =K$7*K43*$E28 -> 27.308685 | L28: =L$7*L43*$E28 -> 27.951583 | M28: =M$7*M43*$E28 -> 28.375568 | N28: =N$7*N43*$E28 -> 28.405763 | ... R28: =R$7*R43*$E28 -> 26.449391 | S28: =SUM(G28:R28) -> 314.30024 | T28: =S28/($S$7*E28) -> 0.86109656
B29: =B28+1 -> 10 | C29: ='Room Types'!C16 -> 0 | D29: ='Room Types'!H16 -> 0 | E29: ='Room Types'!D16 -> 0 | G29: =G$7*G44*$E29 -> 0 | H29: =H$7*H44*$E29 -> 0 | I29: =I$7*I44*$E29 -> 0 | J29: =J$7*J44*$E29 -> 0 | K29: =K$7*K44*$E29 -> 0 | L29: =L$7*L44*$E29 -> 0 | M29: =M$7*M44*$E29 -> 0 | N29: =N$7*N44*$E29 -> 0 | ... R29: =R$7*R44*$E29 -> 0 | S29: =SUM(G29:R29) -> 0 | T29: =S29/($S$7*E29) -> #DIV/0!
C30: Total | D30: =SUMPRODUCT(D20:D29,E20:E29)/E30 -> 28.684058 | E30: =SUM(E20:E29) -> 207 | G30: =SUM(G20:G29) -> 5133.6 | H30: =SUM(H20:H29) -> 4876.5554 | I30: =SUM(I20:I29) -> 5199.7493 | J30: =SUM(J20:J29) -> 4419.7608 | K30: =SUM(K20:K29) -> 5652.8978 | L30: =SUM(L20:L29) -> 5785.9776 | M30: =SUM(M20:M29) -> 5873.7426 | N30: =SUM(N20:N29) -> 5879.9929 | ... R30: =SUM(R20:R29) -> 5475.024 | S30: =SUM(G30:R30) -> 65060.15 | T30: =S30/S9 -> 0.86109656
C33: Occupancy
C34: Type | D34: Size (sqm) | E34: Rooms
B35: 1 | C35: =C20 -> King | D35: =D20 -> 27 | E35: =E20 -> 100 | G35: 0.8 | H35: =$G35*H$46 -> 0.84136567 | I35: =$G35*I$46 -> 0.81030844 | J35: =$G35*J$46 -> 0.71171672 | K35: =$G35*K$46 -> 0.88092532 | L35: =$G35*L$46 -> 0.93171943 | M35: =$G35*M$46 -> 0.91534091 | N35: =$G35*N$46 -> 0.91631494 | O35: =$G35*O$46 -> 0.93150974 | ... R35: =$G35*R$46 -> 0.85320617 | S35: =S20/(E20*$S$7) -> 0.86109656
B36: =B35+1 -> 2 | C36: =C21 -> 0 | D36: =D21 -> 0 | E36: =E21 -> 0 | H36: =$G36*H$46 -> 0 | I36: =$G36*I$46 -> 0 | J36: =$G36*J$46 -> 0 | K36: =$G36*K$46 -> 0 | L36: =$G36*L$46 -> 0 | M36: =$G36*M$46 -> 0 | N36: =$G36*N$46 -> 0 | O36: =$G36*O$46 -> 0 | ... R36: =$G36*R$46 -> 0 | S36: =S21/(E21*$S$7) -> #DIV/0!
B37: =B36+1 -> 3 | C37: =C22 -> Double Double | D37: =D22 -> 28.3 | E37: =E22 -> 100 | G37: 0.8 | H37: =$G37*H$46 -> 0.84136567 | I37: =$G37*I$46 -> 0.81030844 | J37: =$G37*J$46 -> 0.71171672 | K37: =$G37*K$46 -> 0.88092532 | L37: =$G37*L$46 -> 0.93171943 | M37: =$G37*M$46 -> 0.91534091 | N37: =$G37*N$46 -> 0.91631494 | O37: =$G37*O$46 -> 0.93150974 | ... R37: =$G37*R$46 -> 0.85320617 | S37: =S22/(E22*$S$7) -> 0.86109656
B38: =B37+1 -> 4 | C38: =C23 -> 0 | D38: =D23 -> 0 | E38: =E23 -> 0 | H38: =$G38*H$46 -> 0 | I38: =$G38*I$46 -> 0 | J38: =$G38*J$46 -> 0 | K38: =$G38*K$46 -> 0 | L38: =$G38*L$46 -> 0 | M38: =$G38*M$46 -> 0 | N38: =$G38*N$46 -> 0 | O38: =$G38*O$46 -> 0 | ... R38: =$G38*R$46 -> 0 | S38: =S23/(E23*$S$7) -> #DIV/0!
B39: =B38+1 -> 5 | C39: =C24 -> 0 | D39: =D24 -> 0 | E39: =E24 -> 0 | H39: =$G39*H$46 -> 0 | I39: =$G39*I$46 -> 0 | J39: =$G39*J$46 -> 0 | K39: =$G39*K$46 -> 0 | L39: =$G39*L$46 -> 0 | M39: =$G39*M$46 -> 0 | N39: =$G39*N$46 -> 0 | O39: =$G39*O$46 -> 0 | ... R39: =$G39*R$46 -> 0 | S39: =S24/(E24*$S$7) -> #DIV/0!
B40: =B39+1 -> 6 | C40: =C25 -> 0 | D40: =D25 -> 0 | E40: =E25 -> 0 | H40: =$G40*H$46 -> 0 | I40: =$G40*I$46 -> 0 | J40: =$G40*J$46 -> 0 | K40: =$G40*K$46 -> 0 | L40: =$G40*L$46 -> 0 | M40: =$G40*M$46 -> 0 | N40: =$G40*N$46 -> 0 | O40: =$G40*O$46 -> 0 | ... R40: =$G40*R$46 -> 0 | S40: =S25/(E25*$S$7) -> #DIV/0!
B41: =B40+1 -> 7 | C41: =C26 -> Junior Suite | D41: =D26 -> 54 | E41: =E26 -> 5 | G41: 0.8 | H41: =$G41*H$46 -> 0.84136567 | I41: =$G41*I$46 -> 0.81030844 | J41: =$G41*J$46 -> 0.71171672 | K41: =$G41*K$46 -> 0.88092532 | L41: =$G41*L$46 -> 0.93171943 | M41: =$G41*M$46 -> 0.91534091 | N41: =$G41*N$46 -> 0.91631494 | O41: =$G41*O$46 -> 0.93150974 | ... R41: =$G41*R$46 -> 0.85320617 | S41: =S26/(E26*$S$7) -> 0.86109656
B42: =B41+1 -> 8 | C42: =C27 -> Family Suite | D42: =D27 -> 56.6 | E42: =E27 -> 1 | G42: 0.8 | H42: =$G42*H$46 -> 0.84136567 | I42: =$G42*I$46 -> 0.81030844 | J42: =$G42*J$46 -> 0.71171672 | K42: =$G42*K$46 -> 0.88092532 | L42: =$G42*L$46 -> 0.93171943 | M42: =$G42*M$46 -> 0.91534091 | N42: =$G42*N$46 -> 0.91631494 | O42: =$G42*O$46 -> 0.93150974 | ... R42: =$G42*R$46 -> 0.85320617 | S42: =S27/(E27*$S$7) -> 0.86109656
B43: =B42+1 -> 9 | C43: =C28 -> Exec. Suite | D43: =D28 -> 81 | E43: =E28 -> 1 | G43: 0.8 | H43: =$G43*H$46 -> 0.84136567 | I43: =$G43*I$46 -> 0.81030844 | J43: =$G43*J$46 -> 0.71171672 | K43: =$G43*K$46 -> 0.88092532 | L43: =$G43*L$46 -> 0.93171943 | M43: =$G43*M$46 -> 0.91534091 | N43: =$G43*N$46 -> 0.91631494 | O43: =$G43*O$46 -> 0.93150974 | ... R43: =$G43*R$46 -> 0.85320617 | S43: =S28/(E28*$S$7) -> 0.86109656
B44: =B43+1 -> 10 | C44: =C29 -> 0 | D44: =D29 -> 0 | E44: =E29 -> 0 | H44: =$G44*H$46 -> 0 | I44: =$G44*I$46 -> 0 | J44: =$G44*J$46 -> 0 | K44: =$G44*K$46 -> 0 | L44: =$G44*L$46 -> 0 | M44: =$G44*M$46 -> 0 | N44: =$G44*N$46 -> 0 | O44: =$G44*O$46 -> 0 | ... R44: =$G44*R$46 -> 0 | S44: =S29/(E29*$S$7) -> #DIV/0!
C45: Total | D45: =SUMPRODUCT(D35:D44,E35:E44)/E45 -> 28.684058 | E45: =SUM(E35:E44) -> 207 | G45: =G30/G9 -> 0.8 | H45: =H30/H9 -> 0.84136567 | I45: =I30/I9 -> 0.81030844 | J45: =J30/J9 -> 0.71171672 | K45: =K30/K9 -> 0.88092532 | L45: =L30/L9 -> 0.93171943 | M45: =M30/M9 -> 0.91534091 | N45: =N30/N9 -> 0.91631494 | ... S45: =S30/S9 -> 0.86109656 | T45: =S11 -> 0.86109656
G46: vs. Jan: | H46: =H49 -> 1.0517071 | I46: =I49 -> 1.0128856 | J46: =J49 -> 0.8896459 | K46: =K49 -> 1.1011567 | L46: =L49 -> 1.1646493 | M46: =M49 -> 1.1441761 | N46: =N49 -> 1.1453937 | O46: =O49 -> 1.1643872 | ... R46: =R49 -> 1.0665077
E48: STR 2019 | G48: 0.7958335 | H48: 0.83698373 | I48: 0.80608826 | J48: 0.70801001 | K48: 0.87633736 | L48: 0.92686692 | M48: 0.9105737 | N48: 0.91154265 | O48: 0.92665832 | P48: 0.89692761 | Q48: 0.83178974 | R48: 0.84876257 | S48: 0.85661186 | T48: Year 5
G49: vs. Jan | H49: =H48/$G$48 -> 1.0517071 | I49: =I48/$G$48 -> 1.0128856 | J49: =J48/$G$48 -> 0.8896459 | K49: =K48/$G$48 -> 1.1011567 | L49: =L48/$G$48 -> 1.1646493 | M49: =M48/$G$48 -> 1.1441761 | N49: =N48/$G$48 -> 1.1453937 | O49: =O48/$G$48 -> 1.1643872 | ... R49: =R48/$G$48 -> 1.0665077 | T49: =Proforma!P14 -> 0.95609656
C51: Room Rate
C52: Type | D52: Size (sqm) | E52: Rooms | U52: per sqm
B53: 1 | C53: =C35 -> King | D53: =D35 -> 27 | E53: =E35 -> 100 | G53: 10000 | H53: =$G53*H$64 -> 10000 | I53: =$G53*I$64 -> 10000 | J53: =$G53*J$64 -> 10000 | K53: =$G53*K$64 -> 10000 | L53: =$G53*L$64 -> 10000 | M53: =$G53*M$64 -> 10000 | N53: =$G53*N$64 -> 10000 | O53: =$G53*O$64 -> 10000 | ... R53: =$G53*R$64 -> 10000 | S53: =IFERROR(S89/S20,"") -> 10000 | U53: =IFERROR(S53/D53,"") -> 370.37037
B54: =B53+1 -> 2 | C54: =C36 -> 0 | D54: =D36 -> 0 | E54: =E36 -> 0 | H54: =$G54*H$64 -> 0 | I54: =$G54*I$64 -> 0 | J54: =$G54*J$64 -> 0 | K54: =$G54*K$64 -> 0 | L54: =$G54*L$64 -> 0 | M54: =$G54*M$64 -> 0 | N54: =$G54*N$64 -> 0 | O54: =$G54*O$64 -> 0 | ... R54: =$G54*R$64 -> 0 | S54: =IFERROR(S90/S21,"") | U54: =IFERROR(S54/D54,"")
B55: =B54+1 -> 3 | C55: =C37 -> Double Double | D55: =D37 -> 28.3 | E55: =E37 -> 100 | G55: 10000 | H55: =$G55*H$64 -> 10000 | I55: =$G55*I$64 -> 10000 | J55: =$G55*J$64 -> 10000 | K55: =$G55*K$64 -> 10000 | L55: =$G55*L$64 -> 10000 | M55: =$G55*M$64 -> 10000 | N55: =$G55*N$64 -> 10000 | O55: =$G55*O$64 -> 10000 | ... R55: =$G55*R$64 -> 10000 | S55: =IFERROR(S91/S22,"") -> 10000 | U55: =IFERROR(S55/D55,"") -> 353.35689
B56: =B55+1 -> 4 | C56: =C38 -> 0 | D56: =D38 -> 0 | E56: =E38 -> 0 | H56: =$G56*H$64 -> 0 | I56: =$G56*I$64 -> 0 | J56: =$G56*J$64 -> 0 | K56: =$G56*K$64 -> 0 | L56: =$G56*L$64 -> 0 | M56: =$G56*M$64 -> 0 | N56: =$G56*N$64 -> 0 | O56: =$G56*O$64 -> 0 | ... R56: =$G56*R$64 -> 0 | S56: =IFERROR(S92/S23,"") | U56: =IFERROR(S56/D56,"")
B57: =B56+1 -> 5 | C57: =C39 -> 0 | D57: =D39 -> 0 | E57: =E39 -> 0 | H57: =$G57*H$64 -> 0 | I57: =$G57*I$64 -> 0 | J57: =$G57*J$64 -> 0 | K57: =$G57*K$64 -> 0 | L57: =$G57*L$64 -> 0 | M57: =$G57*M$64 -> 0 | N57: =$G57*N$64 -> 0 | O57: =$G57*O$64 -> 0 | ... R57: =$G57*R$64 -> 0 | S57: =IFERROR(S93/S24,"") | U57: =IFERROR(S57/D57,"")
B58: =B57+1 -> 6 | C58: =C40 -> 0 | D58: =D40 -> 0 | E58: =E40 -> 0 | H58: =$G58*H$64 -> 0 | I58: =$G58*I$64 -> 0 | J58: =$G58*J$64 -> 0 | K58: =$G58*K$64 -> 0 | L58: =$G58*L$64 -> 0 | M58: =$G58*M$64 -> 0 | N58: =$G58*N$64 -> 0 | O58: =$G58*O$64 -> 0 | ... R58: =$G58*R$64 -> 0 | S58: =IFERROR(S94/S25,"") | U58: =IFERROR(S58/D58,"")
B59: =B58+1 -> 7 | C59: =C41 -> Junior Suite | D59: =D41 -> 54 | E59: =E41 -> 5 | G59: 10000 | H59: =$G59*H$64 -> 10000 | I59: =$G59*I$64 -> 10000 | J59: =$G59*J$64 -> 10000 | K59: =$G59*K$64 -> 10000 | L59: =$G59*L$64 -> 10000 | M59: =$G59*M$64 -> 10000 | N59: =$G59*N$64 -> 10000 | O59: =$G59*O$64 -> 10000 | ... R59: =$G59*R$64 -> 10000 | S59: =IFERROR(S95/S26,"") -> 10000 | U59: =IFERROR(S59/D59,"") -> 185.18519
B60: =B59+1 -> 8 | C60: =C42 -> Family Suite | D60: =D42 -> 56.6 | E60: =E42 -> 1 | G60: 10000 | H60: =$G60*H$64 -> 10000 | I60: =$G60*I$64 -> 10000 | J60: =$G60*J$64 -> 10000 | K60: =$G60*K$64 -> 10000 | L60: =$G60*L$64 -> 10000 | M60: =$G60*M$64 -> 10000 | N60: =$G60*N$64 -> 10000 | O60: =$G60*O$64 -> 10000 | ... R60: =$G60*R$64 -> 10000 | S60: =IFERROR(S96/S27,"") -> 10000 | U60: =IFERROR(S60/D60,"") -> 176.67845
B61: =B60+1 -> 9 | C61: =C43 -> Exec. Suite | D61: =D43 -> 81 | E61: =E43 -> 1 | G61: 10000 | H61: =$G61*H$64 -> 10000 | I61: =$G61*I$64 -> 10000 | J61: =$G61*J$64 -> 10000 | K61: =$G61*K$64 -> 10000 | L61: =$G61*L$64 -> 10000 | M61: =$G61*M$64 -> 10000 | N61: =$G61*N$64 -> 10000 | O61: =$G61*O$64 -> 10000 | ... R61: =$G61*R$64 -> 10000 | S61: =IFERROR(S97/S28,"") -> 10000 | U61: =IFERROR(S61/D61,"") -> 123.45679
B62: =B61+1 -> 10 | C62: =C44 -> 0 | D62: =D44 -> 0 | E62: =E44 -> 0 | H62: =$G62*H$64 -> 0 | I62: =$G62*I$64 -> 0 | J62: =$G62*J$64 -> 0 | K62: =$G62*K$64 -> 0 | L62: =$G62*L$64 -> 0 | M62: =$G62*M$64 -> 0 | N62: =$G62*N$64 -> 0 | O62: =$G62*O$64 -> 0 | ... R62: =$G62*R$64 -> 0 | S62: =IFERROR(S98/S29,"") | U62: =IFERROR(S62/D62,"")
C63: Total | D63: =SUMPRODUCT(D53:D62,E53:E62)/E63 -> 28.684058 | E63: =SUM(E53:E62) -> 207 | G63: =G99/G30 -> 10000 | H63: =H99/H30 -> 10000 | I63: =I99/I30 -> 10000 | J63: =J99/J30 -> 10000 | K63: =K99/K30 -> 10000 | L63: =L99/L30 -> 10000 | M63: =M99/M30 -> 10000 | N63: =N99/N30 -> 10000 | ... S63: =S99/S30 -> 10000 | T63: =S12 -> 10000 | U63: =IFERROR(S63/D63,"") -> 348.62571
G64: vs. Jan: | H64: 1 | I64: 1 | J64: 1 | K64: 1 | L64: 1 | M64: 1 | N64: 1 | O64: 1 | P64: 1 | Q64: 1 | R64: 1 | S64: =S63/G63-1 -> 0
E66: STR 2019 | G66: 13173.255 | H66: 13861.137 | I66: 13103.672 | J66: 15172.299 | K66: 16791.237 | L66: 15450.269 | M66: 18233.044 | N66: 21990.171 | O66: 18457.797 | P66: 14907.203 | Q66: 12900.364 | R66: 13380.618 | S66: 13487.615 | T66: Year 5
G67: vs. Jan | H67: =H66/$G$66 -> 1.052218 | I67: =I66/$G$66 -> 0.99471786 | J67: =J66/$G$66 -> 1.1517501 | K67: =K66/$G$66 -> 1.274646 | L67: =L66/$G$66 -> 1.1728512 | M67: =M66/$G$66 -> 1.3840956 | N67: =N66/$G$66 -> 1.6693043 | O67: =O66/$G$66 -> 1.4011569 | ... R67: =R66/$G$66 -> 1.0157412 | T67: =Proforma!P15 -> 11037.604
C69: Rev PAR
C70: Type | D70: Size (sqm) | E70: Rooms | U70: per sqm
B71: 1 | C71: =C53 -> King | D71: =D53 -> 27 | E71: =E53 -> 100 | G71: =G35*G53 -> 8000 | H71: =H35*H53 -> 8413.6567 | I71: =I35*I53 -> 8103.0844 | J71: =J35*J53 -> 7117.1672 | K71: =K35*K53 -> 8809.2532 | L71: =L35*L53 -> 9317.1943 | M71: =M35*M53 -> 9153.4091 | N71: =N35*N53 -> 9163.1494 | ... S71: =S35*S53 -> 8610.9656 | U71: =IFERROR(S71/D71,"") -> 318.92465
B72: =B71+1 -> 2 | C72: =C54 -> 0 | D72: =D54 -> 0 | E72: =E54 -> 0 | G72: =G36*G54 -> 0 | H72: =H36*H54 -> 0 | I72: =I36*I54 -> 0 | J72: =J36*J54 -> 0 | K72: =K36*K54 -> 0 | L72: =L36*L54 -> 0 | M72: =M36*M54 -> 0 | N72: =N36*N54 -> 0 | ... S72: =S36*S54 -> #DIV/0! | U72: =IFERROR(S72/D72,"")
B73: =B72+1 -> 3 | C73: =C55 -> Double Double | D73: =D55 -> 28.3 | E73: =E55 -> 100 | G73: =G37*G55 -> 8000 | H73: =H37*H55 -> 8413.6567 | I73: =I37*I55 -> 8103.0844 | J73: =J37*J55 -> 7117.1672 | K73: =K37*K55 -> 8809.2532 | L73: =L37*L55 -> 9317.1943 | M73: =M37*M55 -> 9153.4091 | N73: =N37*N55 -> 9163.1494 | ... S73: =S37*S55 -> 8610.9656 | U73: =IFERROR(S73/D73,"") -> 304.2744
B74: =B73+1 -> 4 | C74: =C56 -> 0 | D74: =D56 -> 0 | E74: =E56 -> 0 | G74: =G38*G56 -> 0 | H74: =H38*H56 -> 0 | I74: =I38*I56 -> 0 | J74: =J38*J56 -> 0 | K74: =K38*K56 -> 0 | L74: =L38*L56 -> 0 | M74: =M38*M56 -> 0 | N74: =N38*N56 -> 0 | ... S74: =S38*S56 -> #DIV/0! | U74: =IFERROR(S74/D74,"")
B75: =B74+1 -> 5 | C75: =C57 -> 0 | D75: =D57 -> 0 | E75: =E57 -> 0 | G75: =G39*G57 -> 0 | H75: =H39*H57 -> 0 | I75: =I39*I57 -> 0 | J75: =J39*J57 -> 0 | K75: =K39*K57 -> 0 | L75: =L39*L57 -> 0 | M75: =M39*M57 -> 0 | N75: =N39*N57 -> 0 | ... S75: =S39*S57 -> #DIV/0! | U75: =IFERROR(S75/D75,"")
B76: =B75+1 -> 6 | C76: =C58 -> 0 | D76: =D58 -> 0 | E76: =E58 -> 0 | G76: =G40*G58 -> 0 | H76: =H40*H58 -> 0 | I76: =I40*I58 -> 0 | J76: =J40*J58 -> 0 | K76: =K40*K58 -> 0 | L76: =L40*L58 -> 0 | M76: =M40*M58 -> 0 | N76: =N40*N58 -> 0 | ... S76: =S40*S58 -> #DIV/0! | U76: =IFERROR(S76/D76,"")
B77: =B76+1 -> 7 | C77: =C59 -> Junior Suite | D77: =D59 -> 54 | E77: =E59 -> 5 | G77: =G41*G59 -> 8000 | H77: =H41*H59 -> 8413.6567 | I77: =I41*I59 -> 8103.0844 | J77: =J41*J59 -> 7117.1672 | K77: =K41*K59 -> 8809.2532 | L77: =L41*L59 -> 9317.1943 | M77: =M41*M59 -> 9153.4091 | N77: =N41*N59 -> 9163.1494 | ... S77: =S41*S59 -> 8610.9656 | U77: =IFERROR(S77/D77,"") -> 159.46233
B78: =B77+1 -> 8 | C78: =C60 -> Family Suite | D78: =D60 -> 56.6 | E78: =E60 -> 1 | G78: =G42*G60 -> 8000 | H78: =H42*H60 -> 8413.6567 | I78: =I42*I60 -> 8103.0844 | J78: =J42*J60 -> 7117.1672 | K78: =K42*K60 -> 8809.2532 | L78: =L42*L60 -> 9317.1943 | M78: =M42*M60 -> 9153.4091 | N78: =N42*N60 -> 9163.1494 | ... S78: =S42*S60 -> 8610.9656 | U78: =IFERROR(S78/D78,"") -> 152.1372
B79: =B78+1 -> 9 | C79: =C61 -> Exec. Suite | D79: =D61 -> 81 | E79: =E61 -> 1 | G79: =G43*G61 -> 8000 | H79: =H43*H61 -> 8413.6567 | I79: =I43*I61 -> 8103.0844 | J79: =J43*J61 -> 7117.1672 | K79: =K43*K61 -> 8809.2532 | L79: =L43*L61 -> 9317.1943 | M79: =M43*M61 -> 9153.4091 | N79: =N43*N61 -> 9163.1494 | ... S79: =S43*S61 -> 8610.9656 | U79: =IFERROR(S79/D79,"") -> 106.30822
B80: =B79+1 -> 10 | C80: =C62 -> 0 | D80: =D62 -> 0 | E80: =E62 -> 0 | G80: =G44*G62 -> 0 | H80: =H44*H62 -> 0 | I80: =I44*I62 -> 0 | J80: =J44*J62 -> 0 | K80: =K44*K62 -> 0 | L80: =L44*L62 -> 0 | M80: =M44*M62 -> 0 | N80: =N44*N62 -> 0 | ... R80: =R44*R62 -> 0 | S80: =IFERROR(S116/S47,"") | U80: =IFERROR(S80/D80,"")
C81: Total | D81: =SUMPRODUCT(D71:D80,E71:E80)/E81 -> 28.684058 | E81: =SUM(E71:E80) -> 207 | G81: =G45*G63 -> 8000 | H81: =H45*H63 -> 8413.6567 | I81: =I45*I63 -> 8103.0844 | J81: =J45*J63 -> 7117.1672 | K81: =K45*K63 -> 8809.2532 | L81: =L45*L63 -> 9317.1943 | M81: =M45*M63 -> 9153.4091 | N81: =N45*N63 -> 9163.1494 | ... R81: =R45*R63 -> 8532.0617 | S81: =IFERROR(S117/S48,"") -> 0 | T81: =T45*T63 -> 8610.9656 | U81: =IFERROR(S81/D81,"") -> 0
G82: vs. Jan: | H82: 1 | I82: 1 | J82: 1 | K82: 1 | L82: 1 | M82: 1 | N82: 1 | O82: 1 | P82: 1 | Q82: 1 | R82: 1 | S82: =S81/G81-1 -> -1
E84: STR 2019 | G84: 10483.718 | H84: 11601.546 | I84: 10562.716 | J84: 10742.139 | K84: 14714.788 | L84: 14320.343 | M84: 16602.531 | N84: 20044.979 | O84: 17104.071 | P84: 13370.682 | Q84: 10730.391 | R84: 11356.967 | S84: 11553.651 | T84: Year 5
G85: vs. Jan | H85: =H84/$G$66 -> 0.88068936 | I85: =I84/$G$66 -> 0.80183039 | J85: =J84/$G$66 -> 0.81545063 | K85: =K84/$G$66 -> 1.1170199 | L85: =L84/$G$66 -> 1.087077 | M85: =M84/$G$66 -> 1.260321 | N85: =N84/$G$66 -> 1.521642 | O85: =O84/$G$66 -> 1.2983937 | ... R85: =R84/$G$66 -> 0.86212307 | T85: =T49*T67 -> 10553.015
C87: Room Revenue
C88: Type | D88: Size (sqm) | E88: Rooms
B89: 1 | C89: =C53 -> King | D89: =D53 -> 27 | E89: =E53 -> 100 | G89: =G53*G20 -> 24800000 | H89: =H53*H20 -> 23558239 | I89: =I53*I20 -> 25119562 | J89: =J53*J20 -> 21351502 | K89: =K53*K20 -> 27308685 | L89: =L53*L20 -> 27951583 | M89: =M53*M20 -> 28375568 | N89: =N53*N20 -> 28405763 | ... R89: =R53*R20 -> 26449391 | S89: =SUM(G89:R89) -> 3.1430024e+08 | T89: =S89/S20 -> 10000
B90: =B89+1 -> 2 | C90: =C54 -> 0 | D90: =D54 -> 0 | E90: =E54 -> 0 | G90: =G54*G21 -> 0 | H90: =H54*H21 -> 0 | I90: =I54*I21 -> 0 | J90: =J54*J21 -> 0 | K90: =K54*K21 -> 0 | L90: =L54*L21 -> 0 | M90: =M54*M21 -> 0 | N90: =N54*N21 -> 0 | ... R90: =R54*R21 -> 0 | S90: =SUM(G90:R90) -> 0 | T90: =S90/S21 -> #DIV/0!
B91: =B90+1 -> 3 | C91: =C55 -> Double Double | D91: =D55 -> 28.3 | E91: =E55 -> 100 | G91: =G55*G22 -> 24800000 | H91: =H55*H22 -> 23558239 | I91: =I55*I22 -> 25119562 | J91: =J55*J22 -> 21351502 | K91: =K55*K22 -> 27308685 | L91: =L55*L22 -> 27951583 | M91: =M55*M22 -> 28375568 | N91: =N55*N22 -> 28405763 | ... R91: =R55*R22 -> 26449391 | S91: =SUM(G91:R91) -> 3.1430024e+08 | T91: =S91/S22 -> 10000
B92: =B91+1 -> 4 | C92: =C56 -> 0 | D92: =D56 -> 0 | E92: =E56 -> 0 | G92: =G56*G23 -> 0 | H92: =H56*H23 -> 0 | I92: =I56*I23 -> 0 | J92: =J56*J23 -> 0 | K92: =K56*K23 -> 0 | L92: =L56*L23 -> 0 | M92: =M56*M23 -> 0 | N92: =N56*N23 -> 0 | ... R92: =R56*R23 -> 0 | S92: =SUM(G92:R92) -> 0 | T92: =S92/S23 -> #DIV/0!
B93: =B92+1 -> 5 | C93: =C57 -> 0 | D93: =D57 -> 0 | E93: =E57 -> 0 | G93: =G57*G24 -> 0 | H93: =H57*H24 -> 0 | I93: =I57*I24 -> 0 | J93: =J57*J24 -> 0 | K93: =K57*K24 -> 0 | L93: =L57*L24 -> 0 | M93: =M57*M24 -> 0 | N93: =N57*N24 -> 0 | ... R93: =R57*R24 -> 0 | S93: =SUM(G93:R93) -> 0 | T93: =S93/S24 -> #DIV/0!
B94: =B93+1 -> 6 | C94: =C58 -> 0 | D94: =D58 -> 0 | E94: =E58 -> 0 | G94: =G58*G25 -> 0 | H94: =H58*H25 -> 0 | I94: =I58*I25 -> 0 | J94: =J58*J25 -> 0 | K94: =K58*K25 -> 0 | L94: =L58*L25 -> 0 | M94: =M58*M25 -> 0 | N94: =N58*N25 -> 0 | ... R94: =R58*R25 -> 0 | S94: =SUM(G94:R94) -> 0 | T94: =S94/S25 -> #DIV/0!
B95: =B94+1 -> 7 | C95: =C59 -> Junior Suite | D95: =D59 -> 54 | E95: =E59 -> 5 | G95: =G59*G26 -> 1240000 | H95: =H59*H26 -> 1177911.9 | I95: =I59*I26 -> 1255978.1 | J95: =J59*J26 -> 1067575.1 | K95: =K59*K26 -> 1365434.3 | L95: =L59*L26 -> 1397579.1 | M95: =M59*M26 -> 1418778.4 | N95: =N59*N26 -> 1420288.1 | ... R95: =R59*R26 -> 1322469.6 | S95: =SUM(G95:R95) -> 15715012 | T95: =S95/S26 -> 10000
B96: =B95+1 -> 8 | C96: =C60 -> Family Suite | D96: =D60 -> 56.6 | E96: =E60 -> 1 | G96: =G60*G27 -> 248000 | H96: =H60*H27 -> 235582.39 | I96: =I60*I27 -> 251195.62 | J96: =J60*J27 -> 213515.02 | K96: =K60*K27 -> 273086.85 | L96: =L60*L27 -> 279515.83 | M96: =M60*M27 -> 283755.68 | N96: =N60*N27 -> 284057.63 | ... R96: =R60*R27 -> 264493.91 | S96: =SUM(G96:R96) -> 3143002.4 | T96: =S96/S27 -> 10000
B97: =B96+1 -> 9 | C97: =C61 -> Exec. Suite | D97: =D61 -> 81 | E97: =E61 -> 1 | G97: =G61*G28 -> 248000 | H97: =H61*H28 -> 235582.39 | I97: =I61*I28 -> 251195.62 | J97: =J61*J28 -> 213515.02 | K97: =K61*K28 -> 273086.85 | L97: =L61*L28 -> 279515.83 | M97: =M61*M28 -> 283755.68 | N97: =N61*N28 -> 284057.63 | ... R97: =R61*R28 -> 264493.91 | S97: =SUM(G97:R97) -> 3143002.4 | T97: =S97/S28 -> 10000
B98: =B97+1 -> 10 | C98: =C62 -> 0 | D98: =D62 -> 0 | E98: =E62 -> 0 | G98: =G62*G29 -> 0 | H98: =H62*H29 -> 0 | I98: =I62*I29 -> 0 | J98: =J62*J29 -> 0 | K98: =K62*K29 -> 0 | L98: =L62*L29 -> 0 | M98: =M62*M29 -> 0 | N98: =N62*N29 -> 0 | ... R98: =R62*R29 -> 0 | S98: =SUM(G98:R98) -> 0 | T98: =S98/S29 -> #DIV/0!
C99: Total | D99: =SUMPRODUCT(D89:D98,E89:E98)/E99 -> 28.684058 | E99: =SUM(E89:E98) -> 207 | G99: =SUM(G89:G98) -> 51336000 | H99: =SUM(H89:H98) -> 48765554 | I99: =SUM(I89:I98) -> 51997493 | J99: =SUM(J89:J98) -> 44197608 | K99: =SUM(K89:K98) -> 56528978 | L99: =SUM(L89:L98) -> 57859776 | M99: =SUM(M89:M98) -> 58737426 | N99: =SUM(N89:N98) -> 58799929 | ... R99: =SUM(R89:R98) -> 54750240 | S99: =SUM(G99:R99) -> 6.506015e+08 | T99: =S99/S30 -> 10000
B103: Proforma KPIs | G103: Year 1 | H103: Year 2 | I103: Year 3 | J103: Year 4 | K103: Year 5
B104: No of Rooms | G104: =Proforma!D11 -> 207 | H104: =Proforma!G11 -> 207 | I104: =Proforma!J11 -> 207 | J104: =Proforma!M11 -> 207 | K104: =Proforma!P11 -> 207
B105: Occupancy | G105: =Proforma!D14 -> 0.86109656 | H105: =Proforma!G14 -> 0.89109656 | I105: =Proforma!J14 -> 0.92109656 | J105: =Proforma!M14 -> 0.94109656 | K105: =Proforma!P14 -> 0.95609656
H108: Welfare | I108: Welfare | J108: Welfare | L108: Welfare
B109: Staffing Salary | G109: Base Mo Salary | H109: Welfare Salary | I109: Transportation | J109: Housing | K109: Bonus | L109: Welfare Bonus | M109: Welfare Total | N109: Total Mo | O109: Total Yr | Q109: Year 1 Month
B110: Administration | D110: Operation Manager | E110: MGR | G110: 500000 | H110: =+G110*0.16 -> 80000 | I110: 10000 | J110: 0 | K110: =+(G110*2)/12 -> 83333.333 | L110: =+K110*0.16 -> 13333.333 | M110: =H110+I110+K110+L110 -> 186666.67 | N110: =M110+G110 -> 686666.67 | O110: =N110*12 -> 8240000 | Q110: =N110*G131 -> 686666.67
B111: Front/Concierge/Bell | D111: Manager | E111: MGR | G111: 0 | H111: =+G111*0.16 -> 0 | I111: 0 | J111: 0 | K111: =+(G111*2)/12 -> 0 | L111: =+K111*0.16 -> 0 | M111: =H111+I111+J111+L111 -> 0 | N111: =M111+G111+K111 -> 0 | O111: =N111*12 -> 0 | Q111: =N111*G132 -> 0
B112: Front/Concierge/Bell | D112: Assistant Manager | E112: AM | G112: 350000 | H112: =+G112*0.16 -> 56000 | I112: 10000 | J112: 0 | K112: =+(G112*2)/12 -> 58333.333 | L112: =+K112*0.16 -> 9333.3333 | M112: =H112+I112+K112+L112 -> 133666.67 | N112: =M112+G112 -> 483666.67 | O112: =N112*12 -> 5804000 | Q112: =N112*G133 -> 483666.67
B113: Front/Concierge/Bell | D113: Team Leader | E113: TL | G113: 250000 | H113: =+G113*0.16 -> 40000 | I113: 0 | J113: 0 | K113: =+(G113*2)/12 -> 41666.667 | L113: =+K113*0.16 -> 6666.6667 | N113: =M113+G113+K113 -> 291666.67 | O113: =N113*12 -> 3500000 | Q113: =N113*G134 -> 291666.67
B114: Front/Concierge/Bell | D114: Guest Service Officer | E114: R&F | G114: 220000 | H114: =+G114*0.16 -> 35200 | I114: 10000 | J114: 0 | K114: =+(G114*2)/12 -> 36666.667 | L114: =+K114*0.16 -> 5866.6667 | M114: =H114+I114+K114+L114 -> 87733.333 | N114: =M114+G114 -> 307733.33 | O114: =N114*12 -> 3692800 | Q114: =N114*G135 -> 923200
B115: Front/Concierge/Bell | D115: Guest Service Officer | E115: PT | G115: 231000 | H115: =+G115*0.16 -> 36960 | I115: =I114 -> 10000 | J115: 0 | K115: =+(G115*0)/12 -> 0 | L115: =+K115*0.16 -> 0 | M115: =H115+I115+K115+L115 -> 46960 | N115: =M115+G115 -> 277960 | O115: =N115*12 -> 3335520 | Q115: =N115*G136 -> 2223680
Q117: =N117*G137 -> 0
...

Sheet Room Types
A1: Hotel xxxx
A2: Room Sizes
C6: Type | D6: No of Rooms | E6: Bed Size (cm) | F6: Room Size (sqm) Range | H6: Avg Room Size (sqm)
B7: 1 | C7: King | D7: 100 | F7: 27 | G7: 27 | H7: =AVERAGE(F7:G7) -> 27 | I7: =D7/$D$17 -> 0.48309179
B8: =B7+1 -> 2
B9: =B8+1 -> 3 | C9: Double Double | D9: 100 | F9: 28.3 | G9: 28.3 | H9: =AVERAGE(F9:G9) -> 28.3 | I9: =D9/$D$17 -> 0.48309179
B10: =B9+1 -> 4
B11: =B10+1 -> 5
B12: =B11+1 -> 6
B13: =B12+1 -> 7 | C13: Junior Suite | D13: 5 | F13: 54 | G13: 54 | H13: =AVERAGE(F13:G13) -> 54 | I13: =D13/$D$17 -> 0.024154589
B14: =B13+1 -> 8 | C14: Family Suite | D14: 1 | F14: 56.6 | G14: 56.6 | H14: =AVERAGE(F14:G14) -> 56.6 | I14: =D14/$D$17 -> 0.0048309179
B15: =B14+1 -> 9 | C15: Exec. Suite | D15: 1 | F15: 81 | G15: 81 | H15: =AVERAGE(F15:G15) -> 81 | I15: =D15/$D$17 -> 0.0048309179
B16: =B15+1 -> 10
C17: Total | D17: =SUM(D7:D16) -> 207 | H17: =SUMPRODUCT(D7:D16,H7:H16)/D17 -> 28.684058 | I17: =SUM(I7:I16) -> 1
G19: Total Room Area | H19: =SUMPRODUCT(H7:H16,D7:D16) -> 5937.6

Sheet Restaurant
A1: ='Room Types'!$A$1 -> Hotel xxxx
A2: ADD
A3: JPY
E6: Month
B7: Year 1 Total | E7: =Rooms!G6 -> 1 | F7: =Rooms!H6 -> 2 | G7: =Rooms!I6 -> 3 | H7: =Rooms!J6 -> 4 | I7: =Rooms!K6 -> 5 | J7: =Rooms!L6 -> 6 | K7: =Rooms!M6 -> 7 | L7: =Rooms!N6 -> 8 | ... P7: =Rooms!R6 -> 12 | Q7: Total
B8: No of Days | E8: =Rooms!G7 -> 31 | F8: =Rooms!H7 -> 28 | G8: =Rooms!I7 -> 31 | H8: =Rooms!J7 -> 30 | I8: =Rooms!K7 -> 31 | J8: =Rooms!L7 -> 30 | K8: =Rooms!M7 -> 31 | L8: =Rooms!N7 -> 31 | ... P8: =Rooms!R7 -> 31 | Q8: =SUM(E8:P8) -> 365
B9: Available Room Nights | E9: =Rooms!G9 -> 6417 | F9: =Rooms!H9 -> 5796 | G9: =Rooms!I9 -> 6417 | H9: =Rooms!J9 -> 6210 | I9: =Rooms!K9 -> 6417 | J9: =Rooms!L9 -> 6210 | K9: =Rooms!M9 -> 6417 | L9: =Rooms!N9 -> 6417 | ... P9: =Rooms!R9 -> 6417 | Q9: =SUM(E9:P9) -> 75555
B10: Occupied Room Nights | E10: =Rooms!G10 -> 5133.6 | F10: =Rooms!H10 -> 4876.5554 | G10: =Rooms!I10 -> 5199.7493 | H10: =Rooms!J10 -> 4419.7608 | I10: =Rooms!K10 -> 5652.8978 | J10: =Rooms!L10 -> 5785.9776 | K10: =Rooms!M10 -> 5873.7426 | L10: =Rooms!N10 -> 5879.9929 | ... P10: =Rooms!R10 -> 5475.024 | Q10: =SUM(E10:P10) -> 65060.15
B11: Occupancy | E11: =Rooms!G11 -> 0.8 | F11: =Rooms!H11 -> 0.84136567 | G11: =Rooms!I11 -> 0.81030844 | H11: =Rooms!J11 -> 0.71171672 | I11: =Rooms!K11 -> 0.88092532 | J11: =Rooms!L11 -> 0.93171943 | K11: =Rooms!M11 -> 0.91534091 | L11: =Rooms!N11 -> 0.91631494 | ... Q11: =Rooms!S11 -> 0.86109656
B12: ADR | E12: =Rooms!G12 -> 10000 | F12: =Rooms!H12 -> 10000 | G12: =Rooms!I12 -> 10000 | H12: =Rooms!J12 -> 10000 | I12: =Rooms!K12 -> 10000 | J12: =Rooms!L12 -> 10000 | K12: =Rooms!M12 -> 10000 | L12: =Rooms!N12 -> 10000 | ... Q12: =Rooms!S12 -> 10000
B13: RevPar | E13: =Rooms!G13 -> 8000 | F13: =Rooms!H13 -> 8413.6567 | G13: =Rooms!I13 -> 8103.0844 | H13: =Rooms!J13 -> 7117.1672 | I13: =Rooms!K13 -> 8809.2532 | J13: =Rooms!L13 -> 9317.1943 | K13: =Rooms!M13 -> 9153.4091 | L13: =Rooms!N13 -> 9163.1494 | ... Q13: =Rooms!S13 -> 8610.9656
B14: Total Guest Count | D14: =Q14/Q10 -> 2 | E14: =Rooms!G14 -> 10267.2 | F14: =Rooms!H14 -> 9753.1108 | G14: =Rooms!I14 -> 10399.499 | H14: =Rooms!J14 -> 8839.5217 | I14: =Rooms!K14 -> 11305.796 | J14: =Rooms!L14 -> 11571.955 | K14: =Rooms!M14 -> 11747.485 | L14: =Rooms!N14 -> 11759.986 | ... P14: =Rooms!R14 -> 10950.048 | Q14: =SUM(E14:P14) -> 130120.3
B15: No of Guests per Day | E15: =E14/E8 -> 331.2 | F15: =F14/F8 -> 348.32539 | G15: =G14/G8 -> 335.46769 | H15: =H14/H8 -> 294.65072 | I15: =I14/I8 -> 364.70308 | J15: =J14/J8 -> 385.73184 | K15: =K14/K8 -> 378.95114 | L15: =L14/L8 -> 379.35438 | ... Q15: =Q14/Q8 -> 356.49397
S16: Year 1
B17: Total Guest Count | D17: =D14 -> 2 | E17: =E14 -> 10267.2 | F17: =F14 -> 9753.1108 | G17: =G14 -> 10399.499 | H17: =H14 -> 8839.5217 | I17: =I14 -> 11305.796 | J17: =J14 -> 11571.955 | K17: =K14 -> 11747.485 | ... P17: =P14 -> 10950.048 | Q17: =SUM(E17:P17) -> 130120.3 | S17: =Rooms!S14 -> 130120.3
B18: per Day | E18: =E17/E8 -> 331.2 | F18: =F17/F8 -> 348.32539 | G18: =G17/G8 -> 335.46769 | H18: =H17/H8 -> 294.65072 | I18: =I17/I8 -> 364.70308 | J18: =J17/J8 -> 385.73184 | K18: =K17/K8 -> 378.95114 | L18: =L17/L8 -> 379.35438 | ... Q18: =Q17/Q8 -> 356.49397
B20: Breakfast Revenues
B22: No of Seats | D22: 100
B24: Hotel Guest Covers | D24: 0.5 | E24: =$D24*E17 -> 5133.6 | F24: =$D24*F17 -> 4876.5554 | G24: =$D24*G17 -> 5199.7493 | H24: =$D24*H17 -> 4419.7608 | I24: =$D24*I17 -> 5652.8978 | J24: =$D24*J17 -> 5785.9776 | K24: =$D24*K17 -> 5873.7426 | L24: =$D24*L17 -> 5879.9929 | ... P24: =$D24*P17 -> 5475.024 | Q24: =SUM(E24:P24) -> 65060.15 | S24: =Q24/$Q$17 -> 0.5
B25: Hotel Guest Cover / Day | E25: =E24/E8 -> 165.6 | F25: =F24/F8 -> 174.16269 | G25: =G24/G8 -> 167.73385 | H25: =H24/H8 -> 147.32536 | I25: =I24/I8 -> 182.35154 | J25: =J24/J8 -> 192.86592 | K25: =K24/K8 -> 189.47557 | L25: =L24/L8 -> 189.67719 | ... Q25: =Q24/Q8 -> 178.24699
B26: Hotel Guest Revenue | D26: 3000 | E26: =$D26*E24 -> 15400800 | F26: =$D26*F24 -> 14629666 | G26: =$D26*G24 -> 15599248 | H26: =$D26*H24 -> 13259283 | I26: =$D26*I24 -> 16958693 | J26: =$D26*J24 -> 17357933 | K26: =$D26*K24 -> 17621228 | L26: =$D26*L24 -> 17639979 | ... P26: =$D26*P24 -> 16425072 | Q26: =SUM(E26:P26) -> 1.9518045e+08
B28: Walk In Covers | D28: 0 | E28: =$D28*$D22*E$8 -> 0 | F28: =$D28*$D22*F$8 -> 0 | G28: =$D28*$D22*G$8 -> 0 | H28: =$D28*$D22*H$8 -> 0 | I28: =$D28*$D22*I$8 -> 0 | J28: =$D28*$D22*J$8 -> 0 | K28: =$D28*$D22*K$8 -> 0 | L28: =$D28*$D22*L$8 -> 0 | ... P28: =$D28*$D22*P$8 -> 0 | Q28: =SUM(E28:P28) -> 0
B29: Walk In Cover / Day | E29: =E28/E8 -> 0 | F29: =F28/F8 -> 0 | G29: =G28/G8 -> 0 | H29: =H28/H8 -> 0 | I29: =I28/I8 -> 0 | J29: =J28/J8 -> 0 | K29: =K28/K8 -> 0 | L29: =L28/L8 -> 0 | ... Q29: =Q28/Q8 -> 0
B30: Walk In Revenues | D30: =D26 -> 3000 | E30: =$D30*E28 -> 0 | F30: =$D30*F28 -> 0 | G30: =$D30*G28 -> 0 | H30: =$D30*H28 -> 0 | I30: =$D30*I28 -> 0 | J30: =$D30*J28 -> 0 | K30: =$D30*K28 -> 0 | L30: =$D30*L28 -> 0 | ... P30: =$D30*P28 -> 0 | Q30: =SUM(E30:P30) -> 0
B32: Total Covers / Month | E32: =E24+E28 -> 5133.6 | F32: =F24+F28 -> 4876.5554 | G32: =G24+G28 -> 5199.7493 | H32: =H24+H28 -> 4419.7608 | I32: =I24+I28 -> 5652.8978 | J32: =J24+J28 -> 5785.9776 | K32: =K24+K28 -> 5873.7426 | L32: =L24+L28 -> 5879.9929 | ... P32: =P24+P28 -> 5475.024 | Q32: =SUM(E32:P32) -> 65060.15
B33: Average Cover / Day | E33: =E32/E8 -> 165.6 | F33: =F32/F8 -> 174.16269 | G33: =G32/G8 -> 167.73385 | H33: =H32/H8 -> 147.32536 | I33: =I32/I8 -> 182.35154 | J33: =J32/J8 -> 192.86592 | K33: =K32/K8 -> 189.47557 | L33: =L32/L8 -> 189.67719 | ... Q33: =Q32/Q8 -> 178.24699
B34: Average Seat Turnover / Day (x) | E34: =E33/$D$22 -> 1.656 | F34: =F33/$D$22 -> 1.7416269 | G34: =G33/$D$22 -> 1.6773385 | H34: =H33/$D$22 -> 1.4732536 | I34: =I33/$D$22 -> 1.8235154 | J34: =J33/$D$22 -> 1.9286592 | K34: =K33/$D$22 -> 1.8947557 | L34: =L33/$D$22 -> 1.8967719 | ... Q34: =Q33/$D$22 -> 1.7824699
B35: Average Check / Cover | E35: =IFERROR(E36/E32,0) -> 3000 | F35: =IFERROR(F36/F32,0) -> 3000 | G35: =IFERROR(G36/G32,0) -> 3000 | H35: =IFERROR(H36/H32,0) -> 3000 | I35: =IFERROR(I36/I32,0) -> 3000 | J35: =IFERROR(J36/J32,0) -> 3000 | K35: =IFERROR(K36/K32,0) -> 3000 | L35: =IFERROR(L36/L32,0) -> 3000 | ... Q35: =IFERROR(Q36/Q32,0) -> 3000
B36: Total Revenues | E36: =E26+E30 -> 15400800 | F36: =F26+F30 -> 14629666 | G36: =G26+G30 -> 15599248 | H36: =H26+H30 -> 13259283 | I36: =I26+I30 -> 16958693 | J36: =J26+J30 -> 17357933 | K36: =K26+K30 -> 17621228 | L36: =L26+L30 -> 17639979 | ... P36: =P26+P30 -> 16425072 | Q36: =SUM(E36:P36) -> 1.9518045e+08
B39: Lunch Revenues
B41: No of Seats | D41: 100
B43: Hotel Guest Covers | D43: 0.05 | E43: =$D43*E17 -> 513.36 | F43: =$D43*F17 -> 487.65554 | G43: =$D43*G17 -> 519.97493 | H43: =$D43*H17 -> 441.97608 | I43: =$D43*I17 -> 565.28978 | J43: =$D43*J17 -> 578.59776 | K43: =$D43*K17 -> 587.37426 | L43: =$D43*L17 -> 587.99929 | ... P43: =$D43*P17 -> 547.5024 | Q43: =SUM(E43:P43) -> 6506.015
B44: Hotel Guest Cover / Day | E44: =E43/E8 -> 16.56 | F44: =F43/F8 -> 17.416269 | G44: =G43/G8 -> 16.773385 | H44: =H43/H8 -> 14.732536 | I44: =I43/I8 -> 18.235154 | J44: =J43/J8 -> 19.286592 | K44: =K43/K8 -> 18.947557 | L44: =L43/L8 -> 18.967719 | ... Q44: =Q43/Q8 -> 17.824699
B45: Hotel Guest Revenue | D45: 3000 | E45: =$D45*E43 -> 1540080 | F45: =$D45*F43 -> 1462966.6 | G45: =$D45*G43 -> 1559924.8 | H45: =$D45*H43 -> 1325928.3 | I45: =$D45*I43 -> 1695869.3 | J45: =$D45*J43 -> 1735793.3 | K45: =$D45*K43 -> 1762122.8 | L45: =$D45*L43 -> 1763997.9 | ... P45: =$D45*P43 -> 1642507.2 | Q45: =SUM(E45:P45) -> 19518045
B47: Walk In Covers | D47: 0.7 | E47: =$D47*$D41*E$8 -> 2170 | F47: =$D47*$D41*F$8 -> 1960 | G47: =$D47*$D41*G$8 -> 2170 | H47: =$D47*$D41*H$8 -> 2100 | I47: =$D47*$D41*I$8 -> 2170 | J47: =$D47*$D41*J$8 -> 2100 | K47: =$D47*$D41*K$8 -> 2170 | L47: =$D47*$D41*L$8 -> 2170 | ... P47: =$D47*$D41*P$8 -> 2170 | Q47: =SUM(E47:P47) -> 25550
B48: Walk In Cover / Day | E48: =E47/E8 -> 70 | F48: =F47/F8 -> 70 | G48: =G47/G8 -> 70 | H48: =H47/H8 -> 70 | I48: =I47/I8 -> 70 | J48: =J47/J8 -> 70 | K48: =K47/K8 -> 70 | L48: =L47/L8 -> 70 | ... Q48: =Q47/Q8 -> 70
B49: Walk In Revenues | D49: =D45 -> 3000 | E49: =$D49*E47 -> 6510000 | F49: =$D49*F47 -> 5880000 | G49: =$D49*G47 -> 6510000 | H49: =$D49*H47 -> 6300000 | I49: =$D49*I47 -> 6510000 | J49: =$D49*J47 -> 6300000 | K49: =$D49*K47 -> 6510000 | L49: =$D49*L47 -> 6510000 | ... P49: =$D49*P47 -> 6510000 | Q49: =SUM(E49:P49) -> 76650000
B51: Total Covers / Month | E51: =E43+E47 -> 2683.36 | F51: =F43+F47 -> 2447.6555 | G51: =G43+G47 -> 2689.9749 | H51: =H43+H47 -> 2541.9761 | I51: =I43+I47 -> 2735.2898 | J51: =J43+J47 -> 2678.5978 | K51: =K43+K47 -> 2757.3743 | L51: =L43+L47 -> 2757.9993 | ... P51: =P43+P47 -> 2717.5024 | Q51: =SUM(E51:P51) -> 32056.015
B52: Average Cover / Day | E52: =E51/E8 -> 86.56 | F52: =F51/F8 -> 87.416269 | G52: =G51/G8 -> 86.773385 | H52: =H51/H8 -> 84.732536 | I52: =I51/I8 -> 88.235154 | J52: =J51/J8 -> 89.286592 | K52: =K51/K8 -> 88.947557 | L52: =L51/L8 -> 88.967719 | ... Q52: =Q51/Q8 -> 87.824699
B53: Average Seat Turnover / Day (x) | E53: =E52/$D$41 -> 0.8656 | F53: =F52/$D$41 -> 0.87416269 | G53: =G52/$D$41 -> 0.86773385 | H53: =H52/$D$41 -> 0.84732536 | I53: =I52/$D$41 -> 0.88235154 | J53: =J52/$D$41 -> 0.89286592 | K53: =K52/$D$41 -> 0.88947557 | L53: =L52/$D$41 -> 0.88967719 | ... Q53: =Q52/$D$41 -> 0.87824699
B54: Average Check / Cover | E54: =IFERROR(E55/E51,0) -> 3000 | F54: =IFERROR(F55/F51,0) -> 3000 | G54: =IFERROR(G55/G51,0) -> 3000 | H54: =IFERROR(H55/H51,0) -> 3000 | I54: =IFERROR(I55/I51,0) -> 3000 | J54: =IFERROR(J55/J51,0) -> 3000 | K54: =IFERROR(K55/K51,0) -> 3000 | L54: =IFERROR(L55/L51,0) -> 3000 | ... Q54: =IFERROR(Q55/Q51,0) -> 3000
B55: Total Revenues | E55: =E45+E49 -> 8050080 | F55: =F45+F49 -> 7342966.6 | G55: =G45+G49 -> 8069924.8 | H55: =H45+H49 -> 7625928.3 | I55: =I45+I49 -> 8205869.3 | J55: =J45+J49 -> 8035793.3 | K55: =K45+K49 -> 8272122.8 | L55: =L45+L49 -> 8273997.9 | ... P55: =P45+P49 -> 8152507.2 | Q55: =SUM(E55:P55) -> 96168045
B58: Dinner Revenues
B60: No of Seats | D60: 100
B62: Hotel Guest Covers | D62: 0.3 | E62: =$D62*E17 -> 3080.16 | F62: =$D62*F17 -> 2925.9332 | G62: =$D62*G17 -> 3119.8496 | H62: =$D62*H17 -> 2651.8565 | I62: =$D62*I17 -> 3391.7387 | J62: =$D62*J17 -> 3471.5866 | K62: =$D62*K17 -> 3524.2456 | L62: =$D62*L17 -> 3527.9958 | ... P62: =$D62*P17 -> 3285.0144 | Q62: =SUM(E62:P62) -> 39036.09 | S62: =Q62/$Q$17 -> 0.3
B63: Hotel Guest Cover / Day | E63: =E62/E8 -> 99.36 | F63: =F62/F8 -> 104.49762 | G63: =G62/G8 -> 100.64031 | H63: =H62/H8 -> 88.395217 | I63: =I62/I8 -> 109.41093 | J63: =J62/J8 -> 115.71955 | K63: =K62/K8 -> 113.68534 | L63: =L62/L8 -> 113.80631 | ... Q63: =Q62/Q8 -> 106.94819
B64: Hotel Guest Revenue | D64: 6000 | E64: =$D64*E62 -> 18480960 | F64: =$D64*F62 -> 17555599 | G64: =$D64*G62 -> 18719097 | H64: =$D64*H62 -> 15911139 | I64: =$D64*I62 -> 20350432 | J64: =$D64*J62 -> 20829519 | K64: =$D64*K62 -> 21145473 | L64: =$D64*L62 -> 21167975 | ... P64: =$D64*P62 -> 19710086 | Q64: =SUM(E64:P64) -> 2.3421654e+08
B66: Walk In Covers | D66: 0.2 | E66: =$D66*$D60*E$8 -> 620 | F66: =$D66*$D60*F$8 -> 560 | G66: =$D66*$D60*G$8 -> 620 | H66: =$D66*$D60*H$8 -> 600 | I66: =$D66*$D60*I$8 -> 620 | J66: =$D66*$D60*J$8 -> 600 | K66: =$D66*$D60*K$8 -> 620 | L66: =$D66*$D60*L$8 -> 620 | ... P66: =$D66*$D60*P$8 -> 620 | Q66: =SUM(E66:P66) -> 7300
B67: Walk In Cover / Day | E67: =E66/E8 -> 20 | F67: =F66/F8 -> 20 | G67: =G66/G8 -> 20 | H67: =H66/H8 -> 20 | I67: =I66/I8 -> 20 | J67: =J66/J8 -> 20 | K67: =K66/K8 -> 20 | L67: =L66/L8 -> 20 | ... Q67: =Q66/Q8 -> 20
B68: Walk In Revenues | D68: =D64 -> 6000 | E68: =$D68*E66 -> 3720000 | F68: =$D68*F66 -> 3360000 | G68: =$D68*G66 -> 3720000 | H68: =$D68*H66 -> 3600000 | I68: =$D68*I66 -> 3720000 | J68: =$D68*J66 -> 3600000 | K68: =$D68*K66 -> 3720000 | L68: =$D68*L66 -> 3720000 | ... P68: =$D68*P66 -> 3720000 | Q68: =SUM(E68:P68) -> 43800000
B70: Total Covers / Month | E70: =E62+E66 -> 3700.16 | F70: =F62+F66 -> 3485.9332 | G70: =G62+G66 -> 3739.8496 | H70: =H62+H66 -> 3251.8565 | I70: =I62+I66 -> 4011.7387 | J70: =J62+J66 -> 4071.5866 | K70: =K62+K66 -> 4144.2456 | L70: =L62+L66 -> 4147.9958 | ... P70: =P62+P66 -> 3905.0144 | Q70: =SUM(E70:P70) -> 46336.09
B71: Average Cover / Day | E71: =E70/E8 -> 119.36 | F71: =F70/F8 -> 124.49762 | G71: =G70/G8 -> 120.64031 | H71: =H70/H8 -> 108.39522 | I71: =I70/I8 -> 129.41093 | J71: =J70/J8 -> 135.71955 | K71: =K70/K8 -> 133.68534 | L71: =L70/L8 -> 133.80631 | ... Q71: =Q70/Q8 -> 126.94819
B72: Average Seat Turnover / Day (x) | E72: =E71/$D$60 -> 1.1936 | F72: =F71/$D$60 -> 1.2449762 | G72: =G71/$D$60 -> 1.2064031 | H72: =H71/$D$60 -> 1.0839522 | I72: =I71/$D$60 -> 1.2941093 | J72: =J71/$D$60 -> 1.3571955 | K72: =K71/$D$60 -> 1.3368534 | L72: =L71/$D$60 -> 1.3380631 | ... Q72: =Q71/$D$60 -> 1.2694819
B73: Average Check / Cover | E73: =IFERROR(E74/E70,0) -> 6000 | F73: =IFERROR(F74/F70,0) -> 6000 | G73: =IFERROR(G74/G70,0) -> 6000 | H73: =IFERROR(H74/H70,0) -> 6000 | I73: =IFERROR(I74/I70,0) -> 6000 | J73: =IFERROR(J74/J70,0) -> 6000 | K73: =IFERROR(K74/K70,0) -> 6000 | L73: =IFERROR(L74/L70,0) -> 6000 | ... Q73: =IFERROR(Q74/Q70,0) -> 6000
B74: Total Revenues | E74: =E64+E68 -> 22200960 | F74: =F64+F68 -> 20915599 | G74: =G64+G68 -> 22439097 | H74: =H64+H68 -> 19511139 | I74: =I64+I68 -> 24070432 | J74: =J64+J68 -> 24429519 | K74: =K64+K68 -> 24865473 | L74: =L64+L68 -> 24887975 | ... P74: =P64+P68 -> 23430086 | Q74: =SUM(E74:P74) -> 2.7801654e+08
B77: Dinner Revenues
B79: No of Seats | D79: =D22 -> 100
B81: Hotel Guest Covers | D81: 0 | E81: =$D81*E14 -> 0 | F81: =$D81*F14 -> 0 | G81: =$D81*G14 -> 0 | H81: =$D81*H14 -> 0 | I81: =$D81*I14 -> 0 | J81: =$D81*J14 -> 0 | K81: =$D81*K14 -> 0 | L81: =$D81*L14 -> 0 | ... P81: =$D81*P14 -> 0 | Q81: =SUM(E81:P81) -> 0
B82: Hotel Guest Cover / Day | E82: =E81/E8 -> 0 | F82: =F81/F8 -> 0 | G82: =G81/G8 -> 0 | H82: =H81/H8 -> 0 | I82: =I81/I8 -> 0 | J82: =J81/J8 -> 0 | K82: =K81/K8 -> 0 | L82: =L81/L8 -> 0 | ... Q82: =Q81/Q8 -> 0
B83: Hotel Guest Revenue | D83: 0 | E83: =$D83*E81 -> 0 | F83: =$D83*F81 -> 0 | G83: =$D83*G81 -> 0 | H83: =$D83*H81 -> 0 | I83: =$D83*I81 -> 0 | J83: =$D83*J81 -> 0 | K83: =$D83*K81 -> 0 | L83: =$D83*L81 -> 0 | ... P83: =$D83*P81 -> 0 | Q83: =SUM(E83:P83) -> 0
B85: Walk In Covers | D85: 0 | E85: =$D85*$D79*E$8 -> 0 | F85: =$D85*$D79*F$8 -> 0 | G85: =$D85*$D79*G$8 -> 0 | H85: =$D85*$D79*H$8 -> 0 | I85: =$D85*$D79*I$8 -> 0 | J85: =$D85*$D79*J$8 -> 0 | K85: =$D85*$D79*K$8 -> 0 | L85: =$D85*$D79*L$8 -> 0 | ... P85: =$D85*$D79*P$8 -> 0 | Q85: =SUM(E85:P85) -> 0
B86: Walk In Cover / Day | E86: =E85/E8 -> 0 | F86: =F85/F8 -> 0 | G86: =G85/G8 -> 0 | H86: =H85/H8 -> 0 | I86: =I85/I8 -> 0 | J86: =J85/J8 -> 0 | K86: =K85/K8 -> 0 | L86: =L85/L8 -> 0 | ... Q86: =Q85/Q8 -> 0
B87: Walk In Revenues | D87: =D83 -> 0 | E87: =$D87*E85 -> 0 | F87: =$D87*F85 -> 0 | G87: =$D87*G85 -> 0 | H87: =$D87*H85 -> 0 | I87: =$D87*I85 -> 0 | J87: =$D87*J85 -> 0 | K87: =$D87*K85 -> 0 | L87: =$D87*L85 -> 0 | ... P87: =$D87*P85 -> 0 | Q87: =SUM(E87:P87) -> 0
B89: Total Covers / Month | E89: =E81+E85 -> 0 | F89: =F81+F85 -> 0 | G89: =G81+G85 -> 0 | H89: =H81+H85 -> 0 | I89: =I81+I85 -> 0 | J89: =J81+J85 -> 0 | K89: =K81+K85 -> 0 | L89: =L81+L85 -> 0 | ... P89: =P81+P85 -> 0 | Q89: =SUM(E89:P89) -> 0
B90: Average Cover / Day | E90: =E89/E8 -> 0 | F90: =F89/F8 -> 0 | G90: =G89/G8 -> 0 | H90: =H89/H8 -> 0 | I90: =I89/I8 -> 0 | J90: =J89/J8 -> 0 | K90: =K89/K8 -> 0 | L90: =L89/L8 -> 0 | ... Q90: =Q89/Q8 -> 0
B91: Average Seat Turnover / Day (x) | E91: =E90/$D$79 -> 0 | F91: =F90/$D$79 -> 0 | G91: =G90/$D$79 -> 0 | H91: =H90/$D$79 -> 0 | I91: =I90/$D$79 -> 0 | J91: =J90/$D$79 -> 0 | K91: =K90/$D$79 -> 0 | L91: =L90/$D$79 -> 0 | ... Q91: =Q90/$D$79 -> 0
B92: Average Check / Cover | E92: =E93/E89 -> #DIV/0! | F92: =F93/F89 -> #DIV/0! | G92: =G93/G89 -> #DIV/0! | H92: =H93/H89 -> #DIV/0! | I92: =I93/I89 -> #DIV/0! | J92: =J93/J89 -> #DIV/0! | K92: =K93/K89 -> #DIV/0! | L92: =L93/L89 -> #DIV/0! | ... Q92: =Q93/Q89 -> #DIV/0!
B93: Total Revenues | E93: =E83+E87 -> 0 | F93: =F83+F87 -> 0 | G93: =G83+G87 -> 0 | H93: =H83+H87 -> 0 | I93: =I83+I87 -> 0 | J93: =J83+J87 -> 0 | K93: =K83+K87 -> 0 | L93: =L83+L87 -> 0 | ... P93: =P83+P87 -> 0 | Q93: =SUM(E93:P93) -> 0
B96: Revenues
B97: Breakfast | E97: =E36 -> 15400800 | F97: =F36 -> 14629666 | G97: =G36 -> 15599248 | H97: =H36 -> 13259283 | I97: =I36 -> 16958693 | J97: =J36 -> 17357933 | K97: =K36 -> 17621228 | L97: =L36 -> 17639979 | ... P97: =P36 -> 16425072 | Q97: =SUM(E97:P97) -> 1.9518045e+08
B98: Lunch | E98: =E55 -> 8050080 | F98: =F55 -> 7342966.6 | G98: =G55 -> 8069924.8 | H98: =H55 -> 7625928.3 | I98: =I55 -> 8205869.3 | J98: =J55 -> 8035793.3 | K98: =K55 -> 8272122.8 | L98: =L55 -> 8273997.9 | ... Q98: =Q55 -> 96168045
B99: Dinner | E99: =E74 -> 22200960 | F99: =F74 -> 20915599 | G99: =G74 -> 22439097 | H99: =H74 -> 19511139 | I99: =I74 -> 24070432 | J99: =J74 -> 24429519 | K99: =K74 -> 24865473 | L99: =L74 -> 24887975 | ... P99: =P74 -> 23430086 | Q99: =SUM(E99:P99) -> 2.7801654e+08
B100: Total | E100: =SUM(E97:E99) -> 45651840 | F100: =SUM(F97:F99) -> 42888232 | G100: =SUM(G97:G99) -> 46108270 | H100: =SUM(H97:H99) -> 40396350 | I100: =SUM(I97:I99) -> 49234995 | J100: =SUM(J97:J99) -> 49823246 | K100: =SUM(K97:K99) -> 50758824 | L100: =SUM(L97:L99) -> 50801951 | ... P100: =SUM(P97:P99) -> 48007665 | Q100: =SUM(E100:P100) -> 5.6936504e+08
B103: Avg Covers per Day
B104: Breakfast | E104: =E33 -> 165.6 | F104: =F33 -> 174.16269 | G104: =G33 -> 167.73385 | H104: =H33 -> 147.32536 | I104: =I33 -> 182.35154 | J104: =J33 -> 192.86592 | K104: =K33 -> 189.47557 | L104: =L33 -> 189.67719 | ... Q104: =Q33 -> 178.24699
B105: Lunch | E105: =E52 -> 86.56 | F105: =F52 -> 87.416269 | G105: =G52 -> 86.773385 | H105: =H52 -> 84.732536 | I105: =I52 -> 88.235154 | J105: =J52 -> 89.286592 | K105: =K52 -> 88.947557 | L105: =L52 -> 88.967719 | ... Q105: =Q52 -> 87.824699
B106: Dinner | E106: =E71 -> 119.36 | F106: =F71 -> 124.49762 | G106: =G71 -> 120.64031 | H106: =H71 -> 108.39522 | I106: =I71 -> 129.41093 | J106: =J71 -> 135.71955 | K106: =K71 -> 133.68534 | L106: =L71 -> 133.80631 | ... Q106: =Q71 -> 126.94819
B107: Total | E107: =SUM(E104:E106) -> 371.52 | F107: =SUM(F104:F106) -> 386.07658 | G107: =SUM(G104:G106) -> 375.14754 | H107: =SUM(H104:H106) -> 340.45311 | I107: =SUM(I104:I106) -> 399.99762 | J107: =SUM(J104:J106) -> 417.87207 | K107: =SUM(K104:K106) -> 412.10847 | L107: =SUM(L104:L106) -> 412.45123 | ... Q107: =SUM(Q104:Q106) -> 393.01988
S109: Average Check | T109: % of FB Covers
B110: Total Covers per Month | S110: per Cover
B111: Breakfast | E111: =E32 -> 5133.6 | F111: =F32 -> 4876.5554 | G111: =G32 -> 5199.7493 | H111: =H32 -> 4419.7608 | I111: =I32 -> 5652.8978 | J111: =J32 -> 5785.9776 | K111: =K32 -> 5873.7426 | L111: =L32 -> 5879.9929 | ... P111: =P32 -> 5475.024 | Q111: =SUM(E111:P111) -> 65060.15 | S111: =IFERROR(Q97/Q111,0) -> 3000 | T111: =D24 -> 0.5
B112: Lunch | E112: =E51 -> 2683.36 | F112: =F51 -> 2447.6555 | G112: =G51 -> 2689.9749 | H112: =H51 -> 2541.9761 | I112: =I51 -> 2735.2898 | J112: =J51 -> 2678.5978 | K112: =K51 -> 2757.3743 | L112: =L51 -> 2757.9993 | ... Q112: =Q51 -> 32056.015 | S112: =IFERROR(Q98/Q112,0) -> 3000 | T112: =D43 -> 0.05
B113: Dinner | E113: =E70 -> 3700.16 | F113: =F70 -> 3485.9332 | G113: =G70 -> 3739.8496 | H113: =H70 -> 3251.8565 | I113: =I70 -> 4011.7387 | J113: =J70 -> 4071.5866 | K113: =K70 -> 4144.2456 | L113: =L70 -> 4147.9958 | ... P113: =P70 -> 3905.0144 | Q113: =SUM(E113:P113) -> 46336.09 | S113: =IFERROR(Q99/Q113,0) -> 6000 | T113: =D62 -> 0.3
B114: Total | E114: =SUM(E111:E113) -> 11517.12 | F114: =SUM(F111:F113) -> 10810.144 | G114: =SUM(G111:G113) -> 11629.574 | H114: =SUM(H111:H113) -> 10213.593 | I114: =SUM(I111:I113) -> 12399.926 | J114: =SUM(J111:J113) -> 12536.162 | K114: =SUM(K111:K113) -> 12775.362 | L114: =SUM(L111:L113) -> 12785.988 | ... P114: =SUM(P111:P113) -> 12097.541 | Q114: =SUM(E114:P114) -> 143452.26 | S114: =Q100/Q114 -> 3969.0212 | T114: =Q114/Q14 -> 1.1024587
S115: =Q100/Q114 -> 3969.0212
B117: Proforma KPIs | E117: Year 1 | F117: Year 2 | G117: Year 3 | H117: Year 4 | I117: Year 5
B118: No of Rooms | E118: =Rooms!G104 -> 207 | F118: =Rooms!H104 -> 207 | G118: =Rooms!I104 -> 207 | H118: =Rooms!J104 -> 207 | I118: =Rooms!K104 -> 207
B119: Occupancy | E119: =Rooms!G105 -> 0.86109656 | F119: =Rooms!H105 -> 0.89109656 | G119: =Rooms!I105 -> 0.92109656 | H119: =Rooms!J105 -> 0.94109656 | I119: =Rooms!K105 -> 0.95609656
B122: Staffing Salary | E122: Base Mo Salary | F122: Welfare Salary | G122: Transportation | H122: Housing | I122: Bonus | J122: Welfare Bonus | K122: Welfare Total | L122: Total Mo | M122: Total Yr | O122: Year 1 Month
B123: All Day Dining | C123: Manager | D123: MGR | E123: 500000 | F123: =+E123*0.16 -> 80000 | G123: 10000 | H123: 0 | I123: =+(E123*2)/12 -> 83333.333 | J123: =+I123*0.16 -> 13333.333 | K123: =F123+G123+H123+J123 -> 103333.33 | L123: =K123+E123+I123 -> 686666.67 | M123: =L123*12 -> 8240000 | O123: =L123*E138 -> 0
B124: All Day Dining | C124: Assistant Manager | D124: AM | E124: 350000 | F124: =+E124*0.16 -> 56000 | G124: =G123 -> 10000 | H124: =H123 -> 0 | I124: =+(E124*2)/12 -> 58333.333 | J124: =+I124*0.16 -> 9333.3333 | K124: =F124+G124+H124+J124 -> 75333.333 | L124: =K124+E124+I124 -> 483666.67 | M124: =L124*12 -> 5804000 | O124: =L124*E139 -> 483666.67
B125: All Day Dining | C125: Team Leader | D125: TL | E125: 250000 | F125: =+E125*0.16 -> 40000 | G125: =G124 -> 10000 | H125: =H124 -> 0 | I125: =+(E125*2)/12 -> 41666.667 | J125: =+I125*0.16 -> 6666.6667 | K125: =F125+G125+H125+J125 -> 56666.667 | L125: =K125+E125+I125 -> 348333.33 | M125: =L125*12 -> 4180000 | O125: =L125*E140 -> 348333.33
B126: All Day Dining | C126: Waiter/Waitress | D126: R&F | E126: 220000 | F126: =+E126*0.16 -> 35200 | G126: =G125 -> 10000 | H126: =H125 -> 0 | I126: =+(E126*2)/12 -> 36666.667 | J126: =+I126*0.16 -> 5866.6667 | K126: =F126+G126+H126+J126 -> 51066.667 | L126: =K126+E126+I126 -> 307733.33 | M126: =L126*12 -> 3692800 | O126: =L126*E141 -> 1230933.3
B127: All Day Dining | C127: Waiter/Waitress | D127: PT | E127: 231000 | F127: =+E127*0.16 -> 36960 | G127: =G126 -> 10000 | H127: =H126 -> 0 | I127: =+(E127*0)/12 -> 0 | J127: =+I127*0.16 -> 0 | K127: =F127+G127+H127+J127 -> 46960 | L127: =K127+E127+I127 -> 277960 | M127: =L127*12 -> 3335520 | O127: =L127*E142 -> 3335520
B128: Cullinary-All Day | C128: Chef de Cuisine | D128: MGR | E128: 500000 | F128: =+E128*0.16 -> 80000 | G128: =G127 -> 10000 | H128: =H127 -> 0 | I128: =+(E128*2)/12 -> 83333.333 | J128: =+I128*0.16 -> 13333.333 | K128: =F128+G128+H128+J128 -> 103333.33 | L128: =K128+E128+I128 -> 686666.67 | M128: =L128*12 -> 8240000 | O128: =L128*E143 -> 686666.67
B129: Cullinary-All Day | C129: Sous Chef | D129: AM | E129: 350000 | F129: =+E129*0.16 -> 56000 | G129: =G128 -> 10000 | H129: =H128 -> 0 | I129: =+(E129*2)/12 -> 58333.333 | J129: =+I129*0.16 -> 9333.3333 | K129: =F129+G129+H129+J129 -> 75333.333 | L129: =K129+E129+I129 -> 483666.67 | M129: =L129*12 -> 5804000 | O129: =L129*E144 -> 483666.67
B130: Cullinary-All Day | C130: Chef de Partie | D130: TL | E130: 250000 | F130: =+E130*0.16 -> 40000 | G130: =G129 -> 10000 | H130: =H129 -> 0 | I130: =+(E130*2)/12 -> 41666.667 | J130: =+I130*0.16 -> 6666.6667 | K130: =F130+G130+H130+J130 -> 56666.667 | L130: =K130+E130+I130 -> 348333.33 | M130: =L130*12 -> 4180000 | O130: =L130*E145 -> 348333.33
B131: Cullinary-All Day | C131: Commis | D131: R&F | E131: 220000 | F131: =+E131*0.16 -> 35200 | G131: =G130 -> 10000 | H131: =H130 -> 0 | I131: =+(E131*2)/12 -> 36666.667 | J131: =+I131*0.16 -> 5866.6667 | K131: =F131+G131+H131+J131 -> 51066.667 | L131: =K131+E131+I131 -> 307733.33 | M131: =L131*12 -> 3692800 | O131: =L131*E146 -> 1230933.3
B132: Cullinary-Breakfast Service | C132: Commis | D132: PT | E132: 231000 | F132: =+E132*0.16 -> 36960 | G132: 10000 | H132: 0 | I132: =+(E132*0)/12 -> 0 | J132: =+I132*0.16 -> 0 | K132: =F132+G132+I132+J132 -> 46960 | L132: =K132+E132 -> 277960 | M132: =L132*12 -> 3335520 | O132: =L132*E147 -> 2223680
B134: Total | O134: =SUM(O123:O133) -> 10371733
...

Sheet MOD
A1: ='Room Types'!$A$1 -> Hotel xxxx
A2: Other Revenue
A3: JPY
E6: Month
B7: Year 1 Total | E7: Jan | F7: Feb | G7: Mar | H7: Apr | I7: May | J7: Jun | K7: Jul | L7: Aug | M7: Sep | N7: Oct | O7: Nov | P7: Dec | Q7: Total
B8: No of Days | E8: =Rooms!G7 -> 31 | F8: =Rooms!H7 -> 28 | G8: =Rooms!I7 -> 31 | H8: =Rooms!J7 -> 30 | I8: =Rooms!K7 -> 31 | J8: =Rooms!L7 -> 30 | K8: =Rooms!M7 -> 31 | L8: =Rooms!N7 -> 31 | ... P8: =Rooms!R7 -> 31 | Q8: =SUM(E8:P8) -> 365
B9: Available Room Nights | E9: =Rooms!G9 -> 6417 | F9: =Rooms!H9 -> 5796 | G9: =Rooms!I9 -> 6417 | H9: =Rooms!J9 -> 6210 | I9: =Rooms!K9 -> 6417 | J9: =Rooms!L9 -> 6210 | K9: =Rooms!M9 -> 6417 | L9: =Rooms!N9 -> 6417 | ... P9: =Rooms!R9 -> 6417 | Q9: =SUM(E9:P9) -> 75555
B10: Occupied Room Nights | E10: =Rooms!G10 -> 5133.6 | F10: =Rooms!H10 -> 4876.5554 | G10: =Rooms!I10 -> 5199.7493 | H10: =Rooms!J10 -> 4419.7608 | I10: =Rooms!K10 -> 5652.8978 | J10: =Rooms!L10 -> 5785.9776 | K10: =Rooms!M10 -> 5873.7426 | L10: =Rooms!N10 -> 5879.9929 | ... P10: =Rooms!R10 -> 5475.024 | Q10: =SUM(E10:P10) -> 65060.15
B11: Occupancy | E11: =Rooms!G11 -> 0.8 | F11: =Rooms!H11 -> 0.84136567 | G11: =Rooms!I11 -> 0.81030844 | H11: =Rooms!J11 -> 0.71171672 | I11: =Rooms!K11 -> 0.88092532 | J11: =Rooms!L11 -> 0.93171943 | K11: =Rooms!M11 -> 0.91534091 | L11: =Rooms!N11 -> 0.91631494 | ... Q11: =Rooms!S11 -> 0.86109656
B12: ADR | E12: =Rooms!G12 -> 10000 | F12: =Rooms!H12 -> 10000 | G12: =Rooms!I12 -> 10000 | H12: =Rooms!J12 -> 10000 | I12: =Rooms!K12 -> 10000 | J12: =Rooms!L12 -> 10000 | K12: =Rooms!M12 -> 10000 | L12: =Rooms!N12 -> 10000 | ... Q12: =Rooms!S12 -> 10000
B13: RevPar | E13: =Rooms!G13 -> 8000 | F13: =Rooms!H13 -> 8413.6567 | G13: =Rooms!I13 -> 8103.0844 | H13: =Rooms!J13 -> 7117.1672 | I13: =Rooms!K13 -> 8809.2532 | J13: =Rooms!L13 -> 9317.1943 | K13: =Rooms!M13 -> 9153.4091 | L13: =Rooms!N13 -> 9163.1494 | ... Q13: =Rooms!S13 -> 8610.9656
B14: Total Guest Count | D14: =Q14/Q10 -> 2 | E14: =Rooms!G14 -> 10267.2 | F14: =Rooms!H14 -> 9753.1108 | G14: =Rooms!I14 -> 10399.499 | H14: =Rooms!J14 -> 8839.5217 | I14: =Rooms!K14 -> 11305.796 | J14: =Rooms!L14 -> 11571.955 | K14: =Rooms!M14 -> 11747.485 | L14: =Rooms!N14 -> 11759.986 | ... P14: =Rooms!R14 -> 10950.048 | Q14: =SUM(E14:P14) -> 130120.3
B17: MOD
B19: Revenues
B20: MOD Charge: Yen Per Guest | E20: 50 | F20: 50 | G20: 50 | H20: 50 | I20: 50 | J20: 50 | K20: 50 | L20: 50 | M20: 50 | N20: 50 | O20: 50 | P20: 50 | Q20: 50
B21: No of Guests | E21: =E14 -> 10267.2 | F21: =F14 -> 9753.1108 | G21: =G14 -> 10399.499 | H21: =H14 -> 8839.5217 | I21: =I14 -> 11305.796 | J21: =J14 -> 11571.955 | K21: =K14 -> 11747.485 | L21: =L14 -> 11759.986 | ... P21: =P14 -> 10950.048 | Q21: =SUM(E21:P21) -> 130120.3
B22: MOD Revenue | E22: =E20*E21 -> 513360 | F22: =F20*F21 -> 487655.54 | G22: =G20*G21 -> 519974.93 | H22: =H20*H21 -> 441976.08 | I22: =I20*I21 -> 565289.78 | J22: =J20*J21 -> 578597.76 | K22: =K20*K21 -> 587374.26 | L22: =L20*L21 -> 587999.29 | ... P22: =P20*P21 -> 547502.4 | Q22: =SUM(E22:P22) -> 6506015
B24: COGS% | E24: 0.5
B25: COGS | E25: =$E$24*E22 -> 256680 | F25: =$E$24*F22 -> 243827.77 | G25: =$E$24*G22 -> 259987.46 | H25: =$E$24*H22 -> 220988.04 | I25: =$E$24*I22 -> 282644.89 | J25: =$E$24*J22 -> 289298.88 | K25: =$E$24*K22 -> 293687.13 | L25: =$E$24*L22 -> 293999.65 | ... P25: =$E$24*P22 -> 273751.2 | Q25: =SUM(E25:P25) -> 3253007.5
B28: Tenant Income
B30: Tenant 1
C31: sqm | D31: Tsubo
B32: Area | C32: =D32*3.30578 -> 0 | D32: 0
B33: Rent / Tsubo / Mo | D33: 0 | E33: =$D$32*$D$33 -> 0 | F33: =$D$32*$D$33 -> 0 | G33: =$D$32*$D$33 -> 0 | H33: =$D$32*$D$33 -> 0 | I33: =$D$32*$D$33 -> 0 | J33: =$D$32*$D$33 -> 0 | K33: =$D$32*$D$33 -> 0 | L33: =$D$32*$D$33 -> 0 | ... P33: =$D$32*$D$33 -> 0 | Q33: =SUM(E33:P33) -> 0
B34: Occupancy | D34: 0 | E34: =$D$34*E33 -> 0 | F34: =$D$34*F33 -> 0 | G34: =$D$34*G33 -> 0 | H34: =$D$34*H33 -> 0 | I34: =$D$34*I33 -> 0 | J34: =$D$34*J33 -> 0 | K34: =$D$34*K33 -> 0 | L34: =$D$34*L33 -> 0 | ... P34: =$D$34*P33 -> 0 | Q34: =SUM(E34:P34) -> 0
B37: Tenant 2
C38: sqm | D38: Tsubo
B39: Area | C39: =D39*3.30578 -> 0 | D39: 0
B40: Rent / Tsubo / Mo | D40: 0 | E40: =$D$39*$D$40 -> 0 | F40: =$D$39*$D$40 -> 0 | G40: =$D$39*$D$40 -> 0 | H40: =$D$39*$D$40 -> 0 | I40: =$D$39*$D$40 -> 0 | J40: =$D$39*$D$40 -> 0 | K40: =$D$39*$D$40 -> 0 | L40: =$D$39*$D$40 -> 0 | ... P40: =$D$39*$D$40 -> 0 | Q40: =SUM(E40:P40) -> 0
B41: Occupancy | D41: 0 | E41: =$D$41*E40 -> 0 | F41: =$D$41*F40 -> 0 | G41: =$D$41*G40 -> 0 | H41: =$D$41*H40 -> 0 | I41: =$D$41*I40 -> 0 | J41: =$D$41*J40 -> 0 | K41: =$D$41*K40 -> 0 | L41: =$D$41*L40 -> 0 | ... P41: =$D$41*P40 -> 0 | Q41: =SUM(E41:P41) -> 0
B44: Tenant 3
C45: sqm | D45: Tsubo
B46: Area | C46: =D46*3.30578 -> 0 | D46: 0
B47: Rent / Tsubo / Mo | D47: 0 | E47: =$D$46*$D$47 -> 0 | F47: =$D$46*$D$47 -> 0 | G47: =$D$46*$D$47 -> 0 | H47: =$D$46*$D$47 -> 0 | I47: =$D$46*$D$47 -> 0 | J47: =$D$46*$D$47 -> 0 | K47: =$D$46*$D$47 -> 0 | L47: =$D$46*$D$47 -> 0 | ... P47: =$D$46*$D$47 -> 0 | Q47: =SUM(E47:P47) -> 0
B48: Occupancy | D48: 0 | E48: =$D$48*E47 -> 0 | F48: =$D$48*F47 -> 0 | G48: =$D$48*G47 -> 0 | H48: =$D$48*H47 -> 0 | I48: =$D$48*I47 -> 0 | J48: =$D$48*J47 -> 0 | K48: =$D$48*K47 -> 0 | L48: =$D$48*L47 -> 0 | ... P48: =$D$48*P47 -> 0 | Q48: =SUM(E48:P48) -> 0
B52: Parking Income
B54: Parking
D55: Tsubo
B56: No of Spaces | D56: 48
B57: Parking Fee / Day | D57: 1500 | E57: =$D$56*$D$57*E8 -> 2232000 | F57: =$D$56*$D$57*F8 -> 2016000 | G57: =$D$56*$D$57*G8 -> 2232000 | H57: =$D$56*$D$57*H8 -> 2160000 | I57: =$D$56*$D$57*I8 -> 2232000 | J57: =$D$56*$D$57*J8 -> 2160000 | K57: =$D$56*$D$57*K8 -> 2232000 | L57: =$D$56*$D$57*L8 -> 2232000 | ... P57: =$D$56*$D$57*P8 -> 2232000 | Q57: =SUM(E57:P57) -> 26280000
B58: Occupancy | D58: 0.5 | E58: =$D$58*E57 -> 1116000 | F58: =$D$58*F57 -> 1008000 | G58: =$D$58*G57 -> 1116000 | H58: =$D$58*H57 -> 1080000 | I58: =$D$58*I57 -> 1116000 | J58: =$D$58*J57 -> 1080000 | K58: =$D$58*K57 -> 1116000 | L58: =$D$58*L57 -> 1116000 | ... P58: =$D$58*P57 -> 1116000 | Q58: =SUM(E58:P58) -> 13140000
B64: Staffing Salary | E64: Base Mo Salary | F64: Welfare Salary | G64: Transportation | H64: Housing | I64: Bonus | J64: Welfare Bonus | K64: Welfare Total | L64: Total Mo | M64: Total Yr | O64: Year 1 Month
B65: Other Revenue | C65: Manager | D65: MGR | E65: 0 | F65: =+E65*0.16 -> 0 | G65: 0 | H65: 0 | I65: =+(E65*2)/12 -> 0 | J65: =+I65*0.16 -> 0 | K65: =F65+G65+H65+J65 -> 0 | L65: =K65+E65+I65 -> 0 | M65: =L65*12 -> 0 | O65: =L65*E75 -> 0
B66: Other Revenue | C66: Assistant Manager | D66: AM | E66: 0 | F66: =+E66*0.16 -> 0 | G66: 0 | H66: =H65 -> 0 | I66: =+(E66*2)/12 -> 0 | J66: =+I66*0.16 -> 0 | K66: =F66+G66+H66+J66 -> 0 | L66: =K66+E66+I66 -> 0 | M66: =L66*12 -> 0 | O66: =L66*E76 -> 0
B67: Other Revenue | C67: Team Leader 1 | D67: TL 1 | E67: 0 | F67: =+E67*0.16 -> 0 | G67: 0 | H67: =H66 -> 0 | I67: =+(E67*2)/12 -> 0 | J67: =+I67*0.16 -> 0 | K67: =F67+G67+H67+J67 -> 0 | L67: =K67+E67+I67 -> 0 | M67: =L67*12 -> 0 | O67: =L67*E77 -> 0
B68: Other Revenue | C68: Team Leader 2 | D68: TL 2 | E68: 0 | F68: =+E68*0.16 -> 0 | G68: =G67 -> 0 | H68: =H67 -> 0 | I68: =+(E68*2)/12 -> 0 | J68: =+I68*0.16 -> 0 | K68: =F68+G68+H68+J68 -> 0 | L68: =K68+E68+I68 -> 0 | M68: =L68*12 -> 0 | O68: =L68*E78 -> 0
B69: Other Revenue | C69: Part Time | D69: PT | E69: 0 | F69: =+E69*0.16 -> 0 | G69: =G68 -> 0 | H69: =H68 -> 0 | I69: =+(E69*0)/12 -> 0 | J69: =+I69*0.16 -> 0 | K69: =F69+G69+H69+J69 -> 0 | L69: =K69+E69+I69 -> 0 | M69: =L69*12 -> 0 | O69: =L69*E79 -> 0
B71: Total | O71: =SUM(O65:O69) -> 0
B74: Staffing Personnel | E74: Year 1 | F74: Year 2 | G74: Year 3 | H74: Year 4 | I74: Year 5 | K74: FT/PT | L74: Year 1 | M74: Year 2 | N74: Year 3 | O74: Year 4 | P74: Year 5
B75: Other Revenue | C75: Manager | D75: MGR | E75: 0 | F75: =E75 -> 0 | G75: =F75 -> 0 | H75: =G75 -> 0 | I75: =H75 -> 0 | K75: FT | L75: =L77-L76 -> 0 | M75: =M77-M76 -> 0 | N75: =N77-N76 -> 0 | O75: =O77-O76 -> 0 | P75: =P77-P76 -> 0
B76: Other Revenue | C76: Assistant Manager | D76: AM | E76: 0 | F76: =E76 -> 0 | G76: =F76 -> 0 | H76: =G76 -> 0 | I76: =H76 -> 0 | K76: PT | L76: =E79 -> 0 | M76: =F79 -> 0 | N76: =G79 -> 0 | O76: =H79 -> 0 | P76: =I79 -> 0
B77: Other Revenue | C77: Team Leader 1 | D77: TL 1 | E77: 0 | F77: =E77 -> 0 | G77: =F77 -> 0 | H77: =G77 -> 0 | I77: =H77 -> 0 | K77: Total | L77: =E81 -> 0 | M77: =F81 -> 0 | N77: =G81 -> 0 | O77: =H81 -> 0 | P77: =I81 -> 0
B78: Other Revenue | C78: Team Leader 2 | D78: TL 2 | E78: 0 | F78: =E78 -> 0 | G78: =F78 -> 0 | H78: =G78 -> 0 | I78: =H78 -> 0
B79: Other Revenue | C79: Part Time | D79: PT | E79: 0 | F79: =E79 -> 0 | G79: =F79 -> 0 | H79: =G79 -> 0 | I79: =H79 -> 0
B81: Total | E81: =SUM(E75:E80) -> 0 | F81: =SUM(F75:F80) -> 0 | G81: =SUM(G75:G80) -> 0 | H81: =SUM(H75:H80) -> 0 | I81: =SUM(I75:I80) -> 0
B84: Staffing Personnel Expense | E84: Year 1 | F84: Year 2 | G84: Year 3 | H84: Year 4 | I84: Year 5
B85: Other Revenue | C85: Manager | D85: MGR | E85: =$M65*E75 -> 0 | F85: =$M65*F75 -> 0 | G85: =$M65*G75 -> 0 | H85: =$M65*H75 -> 0 | I85: =$M65*I75 -> 0
B86: Other Revenue | C86: Assistant Manager | D86: AM | E86: =$M66*E76 -> 0 | F86: =$M66*F76 -> 0 | G86: =$M66*G76 -> 0 | H86: =$M66*H76 -> 0 | I86: =$M66*I76 -> 0
B87: Other Revenue | C87: Team Leader 1 | D87: TL 1 | E87: =$M67*E77 -> 0 | F87: =$M67*F77 -> 0 | G87: =$M67*G77 -> 0 | H87: =$M67*H77 -> 0 | I87: =$M67*I77 -> 0
B88: Other Revenue | C88: Team Leader 2 | D88: TL 2 | E88: =$M68*E78 -> 0 | F88: =$M68*F78 -> 0 | G88: =$M68*G78 -> 0 | H88: =$M68*H78 -> 0 | I88: =$M68*I78 -> 0
B89: Other Revenue | C89: Part Time | D89: PT | E89: =$M69*E79 -> 0 | F89: =$M69*F79 -> 0 | G89: =$M69*G79 -> 0 | H89: =$M69*H79 -> 0 | I89: =$M69*I79 -> 0
B91: Total | E91: =SUM(E85:E90) -> 0 | F91: =SUM(F85:F90) -> 0 | G91: =SUM(G85:G90) -> 0 | H91: =SUM(H85:H90) -> 0 | I91: =SUM(I85:I90) -> 0
B94: COGS / Other Costs | E94: Year 1
B95: Revenues | E95: =Q34+Q41+Q48+Q58+Q22 -> 19646015
B96: Personnel Costs | E96: =E91 -> 0
B97: 原価 | E97: =E95*$H$97 -> 9823007.5 | G97: 原価率 | H97: 0.5
B98: その他 | E98: =E95*$H$98 -> 0 | G98: 率 | H98: 0
B101: PL | E101: Year 1
B102: Revenues | E102: =E95 -> 19646015
B103: Payroll | E103: =E96 -> 0 | F103: =E103/$E$102 -> 0
B104: COGS | E104: =E97 -> 9823007.5 | F104: =E104/$E$102 -> 0.5
B105: Other | E105: =E98 -> 0 | F105: =E105/$E$102 -> 0
B106: Total Expenses | E106: =SUM(E103:E105) -> 9823007.5 | F106: =E106/$E$102 -> 0.5
B107: Department Profit | E107: =E102-E106 -> 9823007.5 | F107: =E107/$E$102 -> 0.5
B108: Check | E108: =Proforma!D59 -> 9823007.5
C118: Head Count | E118: Year 1 | G118: Year 2 | I118: Year 3 | K118: Year 4 | M118: Year 5
C119: Other Revenues | E119: No of Staff | F119: Full Salary | G119: No of Staff | H119: Full Salary | I119: No of Staff | J119: Full Salary | K119: No of Staff | L119: Full Salary | M119: No of Staff | N119: Full Salary
C120: =C119 -> Other Revenues | E120: =E81 -> 0 | F120: =E91 -> 0 | G120: =F81 -> 0 | H120: =F91 -> 0 | I120: =G81 -> 0 | J120: =G91 -> 0 | K120: =H81 -> 0 | L120: =H91 -> 0 | M120: =I81 -> 0 | N120: =I91 -> 0
C122: FT | E122: =L75 -> 0 | G122: =M75 -> 0 | I122: =N75 -> 0 | K122: =O75 -> 0 | M122: =P75 -> 0
C123: PT | E123: =L76 -> 0 | G123: =M76 -> 0 | I123: =N76 -> 0 | K123: =O76 -> 0 | M123: =P76 -> 0
C124: Total | E124: =E122+E123 -> 0 | G124: =G122+G123 -> 0 | I124: =I122+I123 -> 0 | K124: =K122+K123 -> 0 | M124: =M122+M123 -> 0

Sheet Undist Expense
A1: ='Room Types'!$A$1 -> Hotel xxxx
A2: Undistributable Expenses
A3: JPY
E6: Month
B7: Year 1 Total | E7: Jan | F7: Feb | G7: Mar | H7: Apr | I7: May | J7: Jun | K7: Jul | L7: Aug | M7: Sep | N7: Oct | O7: Nov | P7: Dec | Q7: Total
B8: No of Days | C8: =Rooms!S7 -> 365 | E8: =Rooms!G7 -> 31 | F8: =Rooms!H7 -> 28 | G8: =Rooms!I7 -> 31 | H8: =Rooms!J7 -> 30 | I8: =Rooms!K7 -> 31 | J8: =Rooms!L7 -> 30 | K8: =Rooms!M7 -> 31 | L8: =Rooms!N7 -> 31 | ... P8: =Rooms!R7 -> 31 | Q8: =SUM(E8:P8) -> 365
B9: Available Room Nights | C9: =Rooms!S9 -> 75555 | E9: =Rooms!G9 -> 6417 | F9: =Rooms!H9 -> 5796 | G9: =Rooms!I9 -> 6417 | H9: =Rooms!J9 -> 6210 | I9: =Rooms!K9 -> 6417 | J9: =Rooms!L9 -> 6210 | K9: =Rooms!M9 -> 6417 | L9: =Rooms!N9 -> 6417 | ... P9: =Rooms!R9 -> 6417 | Q9: =SUM(E9:P9) -> 75555
B10: Occupied Room Nights | C10: =Rooms!S10 -> 65060.15 | E10: =Rooms!G10 -> 5133.6 | F10: =Rooms!H10 -> 4876.5554 | G10: =Rooms!I10 -> 5199.7493 | H10: =Rooms!J10 -> 4419.7608 | I10: =Rooms!K10 -> 5652.8978 | J10: =Rooms!L10 -> 5785.9776 | K10: =Rooms!M10 -> 5873.7426 | L10: =Rooms!N10 -> 5879.9929 | ... P10: =Rooms!R10 -> 5475.024 | Q10: =SUM(E10:P10) -> 65060.15
B11: Occupancy | C11: =C10/C9 -> 0.86109656 | E11: =E10/E9 -> 0.8 | F11: =F10/F9 -> 0.84136567 | G11: =G10/G9 -> 0.81030844 | H11: =H10/H9 -> 0.71171672 | I11: =I10/I9 -> 0.88092532 | J11: =J10/J9 -> 0.93171943 | K11: =K10/K9 -> 0.91534091 | L11: =L10/L9 -> 0.91631494 | ... Q11: =Q10/Q9 -> 0.86109656
B12: ADR | C12: =Rooms!S12 -> 10000 | E12: =Rooms!G12 -> 10000 | F12: =Rooms!H12 -> 10000 | G12: =Rooms!I12 -> 10000 | H12: =Rooms!J12 -> 10000 | I12: =Rooms!K12 -> 10000 | J12: =Rooms!L12 -> 10000 | K12: =Rooms!M12 -> 10000 | L12: =Rooms!N12 -> 10000 | ... Q12: =Rooms!S12 -> 10000
B13: RevPar | C13: =Rooms!S13 -> 8610.9656 | E13: =E12*E11 -> 8000 | F13: =F12*F11 -> 8413.6567 | G13: =G12*G11 -> 8103.0844 | H13: =H12*H11 -> 7117.1672 | I13: =I12*I11 -> 8809.2532 | J13: =J12*J11 -> 9317.1943 | K13: =K12*K11 -> 9153.4091 | L13: =L12*L11 -> 9163.1494 | ... Q13: =Q12*Q11 -> 8610.9656
B14: Total Guest Count | C14: =Rooms!S14 -> 130120.3 | D14: =C14/C10 -> 2 | E14: =Rooms!G14 -> 10267.2 | F14: =Rooms!H14 -> 9753.1108 | G14: =Rooms!I14 -> 10399.499 | H14: =Rooms!J14 -> 8839.5217 | I14: =Rooms!K14 -> 11305.796 | J14: =Rooms!L14 -> 11571.955 | K14: =Rooms!M14 -> 11747.485 | L14: =Rooms!N14 -> 11759.986 | ... P14: =Rooms!R14 -> 10950.048 | Q14: =SUM(E14:P14) -> 130120.3 | R14: =Q14/Q10 -> 2
B17: Revenues | C17: Year 1 Total
B18: Rooms | C18: =Proforma!D27 -> 6.506015e+08
B19: Restaurant | C19: =Proforma!D28 -> 5.6936504e+08
B20: MOD | C20: =Proforma!D29 -> 19646015
B21: Total | C21: =SUM(C18:C20) -> 1.2396126e+09
B22: Check | C22: =Proforma!D30 -> 1.2396126e+09
B24: Proforma KPIs | E24: Year 1 | F24: Year 2 | G24: Year 3 | H24: Year 4 | I24: Year 5
B25: No of Rooms | E25: =Rooms!G104 -> 207 | F25: =Rooms!H104 -> 207 | G25: =Rooms!I104 -> 207 | H25: =Rooms!J104 -> 207 | I25: =Rooms!K104 -> 207
B26: Occupancy | E26: =Rooms!G105 -> 0.86109656 | F26: =Rooms!H105 -> 0.89109656 | G26: =Rooms!I105 -> 0.92109656 | H26: =Rooms!J105 -> 0.94109656 | I26: =Rooms!K105 -> 0.95609656
F28: y | G28: y | H28: y | K28: y
E29: x | I29: x | K29: x | L29: x
B30: Staffing Salary | E30: Base Mo Salary | F30: Welfare Salary | G30: Transportation | H30: Housing | I30: Bonus | J30: Welfare Bonus | K30: Welfare Total | L30: Total Mo | M30: Total Yr | O30: Year 1 Month
B31: A&G
B32: Project Leader | C32: Project Leader | D32: DH | E32: 0 | F32: =+E32*0.16 -> 0 | G32: 0 | H32: 0 | I32: =+(E32*2)/12 -> 0 | J32: =+I32*0.16 -> 0 | K32: =F32+G32+H32+J32 -> 0 | L32: =K32+E32+I32 -> 0 | M32: =L32*12 -> 0 | O32: =L32*E65 -> 0
B33: Administration | C33: Hotel Manager | D33: Manager | E33: 600000 | F33: =+E33*0.16 -> 96000 | G33: 10000 | H33: 0 | I33: =+(E33*2)/12 -> 100000 | J33: =+I33*0.16 -> 16000 | K33: =F33+G33+H33+J33 -> 122000 | L33: =K33+E33+I33 -> 822000 | M33: =L33*12 -> 9864000 | O33: =L33*E66 -> 822000
B34: Executive Office | C34: Assistant to GM | D34: R&F | E34: 0 | F34: =+E34*0.16 -> 0 | G34: 0 | H34: 0 | I34: =+(E34*2)/12 -> 0 | J34: =+I34*0.16 -> 0 | K34: =F34+G34+H34+J34 -> 0 | L34: =K34+E34+I34 -> 0 | M34: =L34*12 -> 0 | O34: =L34*E67 -> 0
B35: Admin & Finance | C35: Dir of Admin & Finance | D35: DH | E35: 0 | F35: =+E35*0.16 -> 0 | G35: 0 | H35: 0 | I35: =+(E35*2)/12 -> 0 | J35: =+I35*0.16 -> 0 | K35: =F35+G35+H35+J35 -> 0 | L35: =K35+E35+I35 -> 0 | M35: =L35*12 -> 0 | O35: =L35*E68 -> 0
B36: Finance | C36: Manager | D36: MGR | E36: 0 | F36: =+E36*0.16 -> 0 | G36: 0 | H36: 0 | I36: =+(E36*2)/12 -> 0 | J36: =+I36*0.16 -> 0 | K36: =F36+G36+H36+J36 -> 0 | L36: =K36+E36+I36 -> 0 | M36: =L36*12 -> 0 | O36: =L36*E69 -> 0
B37: Finance | C37: Assistant Manager | D37: AM | E37: 0 | F37: =+E37*0.16 -> 0 | G37: 0 | H37: 0 | I37: =+(E37*2)/12 -> 0 | J37: =+I37*0.16 -> 0 | K37: =F37+G37+H37+J37 -> 0 | L37: =K37+E37+I37 -> 0 | M37: =L37*12 -> 0 | O37: =L37*E70 -> 0
B38: Finance | C38: Team Leader | D38: TL | E38: 0 | F38: =+E38*0.16 -> 0 | G38: 0 | H38: 0 | I38: =+(E38*2)/12 -> 0 | J38: =+I38*0.16 -> 0 | K38: =F38+G38+H38+J38 -> 0 | L38: =K38+E38+I38 -> 0 | M38: =L38*12 -> 0 | O38: =L38*E71 -> 0
B39: Finance | C39: Finance Officer | D39: R&F | E39: 0 | F39: =+E39*0.16 -> 0 | G39: 0 | H39: 0 | I39: =+(E39*2)/12 -> 0 | J39: =+I39*0.16 -> 0 | K39: =F39+G39+H39+J39 -> 0 | L39: =K39+E39+I39 -> 0 | M39: =L39*12 -> 0 | O39: =L39*E72 -> 0
B40: Information System | C40: Manager | D40: MGR | E40: 0 | F40: =+E40*0.16 -> 0 | G40: 0 | H40: 0 | I40: =+(E40*2)/12 -> 0 | J40: =+I40*0.16 -> 0 | K40: =F40+G40+H40+J40 -> 0 | L40: =K40+E40+I40 -> 0 | M40: =L40*12 -> 0 | O40: =L40*E73 -> 0
B41: Information System | C41: Assistant Manager | D41: AM | E41: 0 | F41: =+E41*0.16 -> 0 | G41: 0 | H41: 0 | I41: =+(E41*2)/12 -> 0 | J41: =+I41*0.16 -> 0 | K41: =F41+G41+H41+J41 -> 0 | L41: =K41+E41+I41 -> 0 | M41: =L41*12 -> 0 | O41: =L41*E74 -> 0
B42: Material | C42: Manager | D42: MGR | E42: 0 | F42: =+E42*0.16 -> 0 | G42: 0 | H42: 0 | I42: =+(E42*2)/12 -> 0 | J42: =+I42*0.16 -> 0 | K42: =F42+G42+H42+J42 -> 0 | L42: =K42+E42+I42 -> 0 | M42: =L42*12 -> 0 | O42: =L42*E75 -> 0
B43: Material | C43: Assistant Manager | D43: AM | E43: 0 | F43: =+E43*0.16 -> 0 | G43: 0 | H43: 0 | I43: =+(E43*2)/12 -> 0 | J43: =+I43*0.16 -> 0 | K43: =F43+G43+H43+J43 -> 0 | L43: =K43+E43+I43 -> 0 | M43: =L43*12 -> 0 | O43: =L43*E76 -> 0
... B49: Learning/Training | C49: Assistant Manager | D49: AM | E49: 0 | F49: =+E49*0.16 -> 0 | G49: 0 | H49: 0 | I49: =+(E49*2)/12 -> 0 | J49: =+I49*0.16 -> 0 | K49: =F49+G49+H49+J49 -> 0 | L49: =K49+E49+I49 -> 0 | M49: =L49*12 -> 0 | O49: =L49*E82 -> 0
F50: =+E50*0.16 -> 0 | I50: =+(E50*2)/12 -> 0 | J50: =+I50*0.16 -> 0
B51: Sales & Marketing
B52: S&M | C52: Marketing Manager | D52: MGR | E52: 0 | F52: =+E52*0.16 -> 0 | G52: 0 | H52: 0 | I52: =+(E52*2)/12 -> 0 | J52: =+I52*0.16 -> 0 | K52: =F52+G52+H52+J52 -> 0 | L52: =K52+E52+I52 -> 0 | M52: =L52*12 -> 0 | O52: =L52*E85 -> 0
B53: Sales | C53: Sales Assistant Manager | D53: AM | E53: 0 | F53: =+E53*0.16 -> 0 | G53: 0 | H53: 0 | I53: =+(E53*2)/12 -> 0 | J53: =+I53*0.16 -> 0 | K53: =F53+G53+H53+J53 -> 0 | L53: =K53+E53+I53 -> 0 | M53: =L53*12 -> 0 | O53: =L53*E86 -> 0
B54: Sales & Marketing | C54: Coordinator/Admin | D54: R&F | E54: 0 | F54: =+E54*0.16 -> 0 | G54: 0 | H54: 0 | I54: =+(E54*2)/12 -> 0 | J54: =+I54*0.16 -> 0 | K54: =F54+G54+H54+J54 -> 0 | L54: =K54+E54+I54 -> 0 | M54: =L54*12 -> 0 | O54: =L54*E87 -> 0
B56: Engineering
B57: ENG & POMEC | C57: Manager | D57: MGR | E57: 0 | F57: =+E57*0.16 -> 0 | G57: 0 | H57: 0 | I57: =+(E57*2)/12 -> 0 | J57: =+I57*0.16 -> 0 | K57: =F57+G57+H57+J57 -> 0 | L57: =K57+E57+I57 -> 0 | M57: =L57*12 -> 0 | O57: =L57*E90 -> 0
B58: ENG & POMEC | C58: Enginering Officer | D58: R&F | E58: 0 | F58: =+E58*0.16 -> 0 | G58: 0 | H58: 0 | I58: =+(E58*2)/12 -> 0 | J58: =+I58*0.16 -> 0 | K58: =F58+G58+H58+J58 -> 0 | L58: =K58+E58+I58 -> 0 | M58: =L58*12 -> 0 | O58: =L58*E91 -> 0
B60: Total | O60: =SUM(O32:O58) -> 822000
B63: Staffing Personnel | E63: Year 1 | F63: Year 2 | G63: Year 3 | H63: Year 4 | I63: Year 5 | L63: FT/PT | M63: Year 1 | N63: Year 2 | O63: Year 3 | P63: Year 4 | Q63: Year 5
B64: A&G | L64: FT | M64: =M66-M65 -> 1 | N64: =N66-N65 -> 1 | O64: =O66-O65 -> 1 | P64: =P66-P65 -> 1 | Q64: =Q66-Q65 -> 1
B65: Project Leader | C65: Project Leader | D65: DH | E65: 0 | F65: =E65 -> 0 | G65: =F65 -> 0 | H65: =G65 -> 0 | I65: =H65 -> 0 | L65: PT | M65: 0 | N65: 0 | O65: 0 | P65: 0 | Q65: 0
B66: Administration | C66: Hotel Manager | D66: Manager | E66: 1 | F66: =E66 -> 1 | G66: =F66 -> 1 | H66: =G66 -> 1 | I66: =H66 -> 1 | L66: Total | M66: =E93 -> 1 | N66: =F93 -> 1 | O66: =G93 -> 1 | P66: =H93 -> 1 | Q66: =I93 -> 1
B67: Executive Office | C67: Assistant to GM | D67: R&F | E67: 0 | F67: =E67 -> 0 | G67: =F67 -> 0 | H67: =G67 -> 0 | I67: =H67 -> 0
B68: Admin & Finance | C68: Dir of Admin & Finance | D68: DH | E68: 0 | F68: =E68 -> 0 | G68: =F68 -> 0 | H68: =G68 -> 0 | I68: =H68 -> 0
B69: Finance | C69: Manager | D69: MGR | E69: 0 | F69: =E69 -> 0 | G69: =F69 -> 0 | H69: =G69 -> 0 | I69: =H69 -> 0
B70: Finance | C70: Assistant Manager | D70: AM | E70: 0 | F70: =E70 -> 0 | G70: =F70 -> 0 | H70: =G70 -> 0 | I70: =H70 -> 0
B71: Finance | C71: Team Leader | D71: TL | E71: 0 | F71: =E71 -> 0 | G71: =F71 -> 0 | H71: =G71 -> 0 | I71: =H71 -> 0
B72: Finance | C72: Finance Officer | D72: R&F | E72: 0 | F72: =E72 -> 0 | G72: =F72 -> 0 | H72: =G72 -> 0 | I72: =H72 -> 0
B73: Information System | C73: Manager | D73: MGR | E73: 0 | F73: =E73 -> 0 | G73: =F73 -> 0 | H73: =G73 -> 0 | I73: =H73 -> 0
B74: Information System | C74: Assistant Manager | D74: AM | E74: 0 | F74: =E74 -> 0 | G74: =F74 -> 0 | H74: =G74 -> 0 | I74: =H74 -> 0
B75: Material | C75: Manager | D75: MGR | E75: 0 | F75: =E75 -> 0 | G75: =F75 -> 0 | H75: =G75 -> 0 | I75: =H75 -> 0
B76: Material | C76: Assistant Manager | D76: AM | E76: 0 | F76: 0 | G76: =F76 -> 0 | H76: =G76 -> 0 | I76: =H76 -> 0
B77: Material | C77: Material Officer | D77: R&F | E77: 0 | F77: =E77 -> 0 | G77: =F77 -> 0 | H77: =G77 -> 0 | I77: =H77 -> 0
B78: Human Resources | C78: Manager | D78: MGR | E78: 0 | F78: =E78 -> 0 | G78: =F78 -> 0 | H78: =G78 -> 0 | I78: =H78 -> 0
B79: Human Resources | C79: Assistant Manager | D79: AM | E79: 0 | F79: =E79 -> 0 | G79: =F79 -> 0 | H79: =G79 -> 0 | I79: =H79 -> 0
B80: Human Resources | C80: HR Officer | D80: R&F | E80: 0 | F80: =E80 -> 0 | G80: =F80 -> 0 | H80: =G80 -> 0 | I80: =H80 -> 0
B81: Learning/Training | C81: Manager | D81: MGR | E81: 0 | F81: =E81 -> 0 | G81: =F81 -> 0 | H81: =G81 -> 0 | I81: =H81 -> 0
B82: Learning/Training | C82: Assistant Manager | D82: AM | E82: 0 | F82: =E82 -> 0 | G82: =F82 -> 0 | H82: =G82 -> 0 | I82: =H82 -> 0
B84: Sales & Marketing
B85: S&M | C85: Marketing Manager | D85: MGR | E85: 0 | F85: =E85 -> 0 | G85: =F85 -> 0 | H85: =G85 -> 0 | I85: =H85 -> 0
B86: Sales | C86: Sales Assistant Manager | D86: AM | E86: 0 | F86: =E86 -> 0 | G86: =F86 -> 0 | H86: =G86 -> 0 | I86: =H86 -> 0
B87: Sales & Marketing | C87: Coordinator/Admin | D87: R&F | E87: 0 | F87: =E87 -> 0 | G87: =F87 -> 0 | H87: =G87 -> 0 | I87: =H87 -> 0
B89: Engineering
B90: ENG & POMEC | C90: Manager | D90: MGR | E90: 0 | F90: =E90 -> 0 | G90: =F90 -> 0 | H90: =G90 -> 0 | I90: =H90 -> 0
B91: ENG & POMEC | C91: Enginering Officer | D91: R&F | E91: 0 | F91: =E91 -> 0 | G91: =F91 -> 0 | H91: =G91 -> 0 | I91: =H91 -> 0
B93: Total | E93: =SUM(E64:E91) -> 1 | F93: =SUM(F64:F91) -> 1 | G93: =SUM(G64:G91) -> 1 | H93: =SUM(H64:H91) -> 1 | I93: =SUM(I64:I91) -> 1
B96: Staffing Personnel Expense | E96: Year 1 | F96: Year 2 | G96: Year 3 | H96: Year 4 | I96: Year 5
B97: A&G
B98: Project Leader | C98: Project Leader | D98: DH | E98: =$M32*E65 -> 0 | F98: =$M32*F65 -> 0 | G98: =$M32*G65 -> 0 | H98: =$M32*H65 -> 0 | I98: =$M32*I65 -> 0
B99: Administration | C99: Hotel Manager | D99: Manager | E99: =$M33*E66 -> 9864000 | F99: =$M33*F66 -> 9864000 | G99: =$M33*G66 -> 9864000 | H99: =$M33*H66 -> 9864000 | I99: =$M33*I66 -> 9864000
B100: Executive Office | C100: Assistant to GM | D100: R&F | E100: =$M34*E67 -> 0 | F100: =$M34*F67 -> 0 | G100: =$M34*G67 -> 0 | H100: =$M34*H67 -> 0 | I100: =$M34*I67 -> 0
B101: Admin & Finance | C101: Dir of Admin & Finance | D101: DH | E101: =$M35*E68 -> 0 | F101: =$M35*F68 -> 0 | G101: =$M35*G68 -> 0 | H101: =$M35*H68 -> 0 | I101: =$M35*I68 -> 0
B102: Finance | C102: Manager | D102: MGR | E102: =$M36*E69 -> 0 | F102: =$M36*F69 -> 0 | G102: =$M36*G69 -> 0 | H102: =$M36*H69 -> 0 | I102: =$M36*I69 -> 0
B103: Finance | C103: Assistant Manager | D103: AM | E103: =$M37*E70 -> 0 | F103: =$M37*F70 -> 0 | G103: =$M37*G70 -> 0 | H103: =$M37*H70 -> 0 | I103: =$M37*I70 -> 0
B104: Finance | C104: Team Leader | D104: TL | E104: =$M38*E71 -> 0 | F104: =$M38*F71 -> 0 | G104: =$M38*G71 -> 0 | H104: =$M38*H71 -> 0 | I104: =$M38*I71 -> 0
B105: Finance | C105: Finance Officer | D105: R&F | E105: =$M39*E72 -> 0 | F105: =$M39*F72 -> 0 | G105: =$M39*G72 -> 0 | H105: =$M39*H72 -> 0 | I105: =$M39*I72 -> 0
B106: Information System | C106: Manager | D106: MGR | E106: =$M40*E73 -> 0 | F106: =$M40*F73 -> 0 | G106: =$M40*G73 -> 0 | H106: =$M40*H73 -> 0 | I106: =$M40*I73 -> 0
B107: Information System | C107: Assistant Manager | D107: AM | E107: =$M41*E74 -> 0 | F107: =$M41*F74 -> 0 | G107: =$M41*G74 -> 0 | H107: =$M41*H74 -> 0 | I107: =$M41*I74 -> 0
B108: Material | C108: Manager | D108: MGR | E108: =$M42*E75 -> 0 | F108: =$M42*F75 -> 0 | G108: =$M42*G75 -> 0 | H108: =$M42*H75 -> 0 | I108: =$M42*I75 -> 0
B109: Material | C109: Assistant Manager | D109: AM | E109: =$M43*E76 -> 0 | F109: =$M43*F76 -> 0 | G109: =$M43*G76 -> 0 | H109: =$M43*H76 -> 0 | I109: =$M43*I76 -> 0
... B115: Learning/Training | C115: Assistant Manager | D115: AM | E115: =$M49*E82 -> 0 | F115: =$M49*F82 -> 0 | G115: =$M49*G82 -> 0 | H115: =$M49*H82 -> 0 | I115: =$M49*I82 -> 0
B117: Sales & Marketing
B118: S&M | C118: Marketing Manager | D118: MGR | E118: =$M52*E85 -> 0 | F118: =$M52*F85 -> 0 | G118: =$M52*G85 -> 0 | H118: =$M52*H85 -> 0 | I118: =$M52*I85 -> 0
B119: Sales | C119: Sales Assistant Manager | D119: AM | E119: =$M53*E86 -> 0 | F119: =$M53*F86 -> 0 | G119: =$M53*G86 -> 0 | H119: =$M53*H86 -> 0 | I119: =$M53*I86 -> 0
B120: Sales & Marketing | C120: Coordinator/Admin | D120: R&F | E120: =$M54*E87 -> 0 | F120: =$M54*F87 -> 0 | G120: =$M54*G87 -> 0 | H120: =$M54*H87 -> 0 | I120: =$M54*I87 -> 0
B122: Engineering
B123: ENG & POMEC | C123: Manager | D123: MGR | E123: =$M57*E90 -> 0 | F123: =$M57*F90 -> 0 | G123: =$M57*G90 -> 0 | H123: =$M57*H90 -> 0 | I123: =$M57*I90 -> 0
B124: ENG & POMEC | C124: Enginering Officer | D124: R&F | E124: =$M58*E91 -> 0 | F124: =$M58*F91 -> 0 | G124: =$M58*G91 -> 0 | H124: =$M58*H91 -> 0 | I124: =$M58*I91 -> 0
B126: Total | E126: =SUM(E97:E124) -> 9864000 | F126: =SUM(F97:F124) -> 9864000 | G126: =SUM(G97:G124) -> 9864000 | H126: =SUM(H97:H124) -> 9864000 | I126: =SUM(I97:I124) -> 9864000
B129: 非配賦費用
B130: 一般管理部門 | C130: クレジットカード手数料 | E130: =C21*H130*J130 -> 15495157 | F130: =E130/C$21 -> 0.0125 | G130: 利用率 | H130: 0.5 | I130: 手数料率 | J130: 0.025
...

Sheet Staffing
A1: ='Undist Expense'!A1 -> Hotel xxxx
A2: Staffing
A3: JPY
B6: Head Count / Salary | C6: Year 1 | E6: Year 2 | G6: Year 3 | I6: Year 4 | K6: Year 5 | N6: Year 1 Month
C7: No of Staff | D7: Full Salary | E7: No of Staff | F7: Full Salary | G7: No of Staff | H7: Full Salary | I7: No of Staff | J7: Full Salary | K7: No of Staff | L7: Full Salary
B9: Rooms | C9: =Rooms!G205 -> 14 | D9: =Rooms!H205 -> 55306560 | E9: =Rooms!I205 -> 14 | F9: =Rooms!J205 -> 55306560 | G9: =Rooms!K205 -> 14 | H9: =Rooms!L205 -> 55306560 | I9: =Rooms!M205 -> 14 | J9: =Rooms!N205 -> 55306560 | ... L9: =Rooms!P205 -> 55306560 | N9: =D9/12 -> 4608880
B11: Restaurant | C11: =Restaurant!E189 -> 33 | D11: =Restaurant!F189 -> 124460800 | E11: =Restaurant!G189 -> 33 | F11: =Restaurant!H189 -> 124460800 | G11: =Restaurant!I189 -> 33 | H11: =Restaurant!J189 -> 124460800 | I11: =Restaurant!K189 -> 33 | J11: =Restaurant!L189 -> 124460800 | ... L11: =Restaurant!N189 -> 124460800 | N11: =D11/12 -> 10371733
B13: Other | C13: =MOD!E81 -> 0 | D13: =MOD!E91 -> 0 | E13: =MOD!F81 -> 0 | F13: =MOD!F91 -> 0 | G13: =MOD!G81 -> 0 | H13: =MOD!G91 -> 0 | I13: =MOD!H81 -> 0 | J13: =MOD!H91 -> 0 | K13: =MOD!I81 -> 0 | L13: =MOD!I91 -> 0 | N13: =D13/12 -> 0
B15: A&G | C15: ='Undist Expense'!E182 -> 1 | D15: ='Undist Expense'!F182 -> 9864000 | E15: ='Undist Expense'!G182 -> 1 | F15: ='Undist Expense'!H182 -> 9864000 | G15: ='Undist Expense'!I182 -> 1 | H15: ='Undist Expense'!J182 -> 9864000 | I15: ='Undist Expense'!K182 -> 1 | J15: ='Undist Expense'!L182 -> 9864000 | ... L15: ='Undist Expense'!N182 -> 9864000 | N15: =D15/12 -> 822000
B17: Sales & Marketing | C17: ='Undist Expense'!E183 -> 0 | D17: ='Undist Expense'!F183 -> 0 | E17: ='Undist Expense'!G183 -> 0 | F17: ='Undist Expense'!H183 -> 0 | G17: ='Undist Expense'!I183 -> 0 | H17: ='Undist Expense'!J183 -> 0 | I17: ='Undist Expense'!K183 -> 0 | J17: ='Undist Expense'!L183 -> 0 | ... L17: ='Undist Expense'!N183 -> 0 | N17: =D17/12 -> 0
B19: Enginnering | C19: ='Undist Expense'!E184 -> 0 | D19: ='Undist Expense'!F184 -> 0 | E19: ='Undist Expense'!G184 -> 0 | F19: ='Undist Expense'!H184 -> 0 | G19: ='Undist Expense'!I184 -> 0 | H19: ='Undist Expense'!J184 -> 0 | I19: ='Undist Expense'!K184 -> 0 | J19: ='Undist Expense'!L184 -> 0 | ... L19: ='Undist Expense'!N184 -> 0 | N19: =D19/12 -> 0
B21: Total | C21: =SUM(C9:C19) -> 48 | D21: =SUM(D9:D19) -> 189631360 | E21: =SUM(E9:E19) -> 48 | F21: =SUM(F9:F19) -> 189631360 | G21: =SUM(G9:G19) -> 48 | H21: =SUM(H9:H19) -> 189631360 | I21: =SUM(I9:I19) -> 48 | J21: =SUM(J9:J19) -> 189631360 | ... L21: =SUM(L9:L19) -> 189631360 | N21: =SUM(N9:N19) -> 15802613
B22: Check | D22: =Proforma!D24 -> 189631360 | F22: =Proforma!G24 -> 189631360 | H22: =Proforma!J24 -> 189631360 | J22: =Proforma!M24 -> 189631360 | L22: =Proforma!P24 -> 189631360 | N22: =D22/12 -> 15802613
B25: Head Count / Salary | C25: Year 1 | E25: Year 2 | G25: Year 3 | I25: Year 4 | K25: Year 5
C26: No of Staff | D26: Full Salary | E26: No of Staff | F26: Full Salary | G26: No of Staff | H26: Full Salary | I26: No of Staff | J26: Full Salary | K26: No of Staff | L26: Full Salary
B28: Rooms | C28: =C9 -> 14 | D28: =D9 -> 55306560 | E28: =E9 -> 14 | F28: =F9 -> 55306560 | G28: =G9 -> 14 | H28: =H9 -> 55306560 | I28: =I9 -> 14 | J28: =J9 -> 55306560 | ... L28: =L9 -> 55306560
B29: Restaurant | C29: =C11 -> 33 | D29: =D11 -> 124460800 | E29: =E11 -> 33 | F29: =F11 -> 124460800 | G29: =G11 -> 33 | H29: =H11 -> 124460800 | I29: =I11 -> 33 | J29: =J11 -> 124460800 | ... L29: =L11 -> 124460800
B30: Other | C30: =C13 -> 0 | D30: =D13 -> 0 | E30: =E13 -> 0 | F30: =F13 -> 0 | G30: =G13 -> 0 | H30: =H13 -> 0 | I30: =I13 -> 0 | J30: =J13 -> 0 | ... L30: =L13 -> 0
B31: Undistributable | C31: =C15+C17+C19 -> 1 | D31: =D15+D17+D19 -> 9864000 | E31: =E15+E17+E19 -> 1 | F31: =F15+F17+F19 -> 9864000 | G31: =G15+G17+G19 -> 1 | H31: =H15+H17+H19 -> 9864000 | I31: =I15+I17+I19 -> 1 | J31: =J15+J17+J19 -> 9864000 | ... L31: =L15+L17+L19 -> 9864000
B32: Total | C32: =SUM(C28:C31) -> 48 | D32: =SUM(D28:D31) -> 189631360 | E32: =SUM(E28:E31) -> 48 | F32: =SUM(F28:F31) -> 189631360 | G32: =SUM(G28:G31) -> 48 | H32: =SUM(H28:H31) -> 189631360 | I32: =SUM(I28:I31) -> 48 | J32: =SUM(J28:J31) -> 189631360 | ... L32: =SUM(L28:L31) -> 189631360
B35: Head Count; FT / PT | C35: Year 1 | E35: Year 2 | G35: Year 3 | I35: Year 4 | K35: Year 5
C36: No of Staff | E36: No of Staff | G36: No of Staff | I36: No of Staff | K36: No of Staff
B38: Rooms | C38: =C39+C40 -> 14 | E38: =E39+E40 -> 14 | G38: =G39+G40 -> 14 | I38: =I39+I40 -> 14 | K38: =K39+K40 -> 14
B39: FT | C39: =Rooms!G207 -> 6 | E39: =Rooms!I207 -> 6 | G39: =Rooms!K207 -> 6 | I39: =Rooms!M207 -> 6 | K39: =Rooms!O207 -> 6
B40: PT | C40: =Rooms!G208 -> 8 | E40: =Rooms!I208 -> 8 | G40: =Rooms!K208 -> 8 | I40: =Rooms!M208 -> 8 | K40: =Rooms!O208 -> 8
B41: Restaurant | C41: =C42+C43 -> 33 | E41: =E42+E43 -> 33 | G41: =G42+G43 -> 33 | I41: =I42+I43 -> 33 | K41: =K42+K43 -> 33
B42: FT | C42: =Restaurant!E191 -> 13 | E42: =Restaurant!G191 -> 13 | G42: =Restaurant!I191 -> 13 | I42: =Restaurant!K191 -> 13 | K42: =Restaurant!M191 -> 13
B43: PT | C43: =Restaurant!E192 -> 20 | E43: =Restaurant!G192 -> 20 | G43: =Restaurant!I192 -> 20 | I43: =Restaurant!K192 -> 20 | K43: =Restaurant!M192 -> 20
B44: Other | C44: =C45+C46 -> 0 | E44: =E45+E46 -> 0 | G44: =G45+G46 -> 0 | I44: =I45+I46 -> 0 | K44: =K45+K46 -> 0
B45: FT | C45: =MOD!E122 -> 0 | E45: =MOD!G122 -> 0 | G45: =MOD!I122 -> 0 | I45: =MOD!K122 -> 0 | K45: =MOD!M122 -> 0
B46: PT | C46: =MOD!E123 -> 0 | E46: =MOD!G123 -> 0 | G46: =MOD!I123 -> 0 | I46: =MOD!K123 -> 0 | K46: =MOD!M123 -> 0
B47: Undistributable | C47: =C48+C49 -> 1 | E47: =E48+E49 -> 1 | G47: =G48+G49 -> 1 | I47: =I48+I49 -> 1 | K47: =K48+K49 -> 1
B48: FT | C48: ='Undist Expense'!E187 -> 1 | E48: ='Undist Expense'!G187 -> 1 | G48: ='Undist Expense'!I187 -> 1 | I48: ='Undist Expense'!K187 -> 1 | K48: ='Undist Expense'!M187 -> 1
B49: PT | C49: ='Undist Expense'!E188 -> 0 | E49: ='Undist Expense'!G188 -> 0 | G49: ='Undist Expense'!I188 -> 0 | I49: ='Undist Expense'!K188 -> 0 | K49: ='Undist Expense'!M188 -> 0
B50: Total | C50: =C51+C52 -> 48 | D50: =C38+C41+C44+C47 -> 48 | E50: =E51+E52 -> 48 | F50: =E38+E41+E44+E47 -> 48 | G50: =G51+G52 -> 48 | H50: =G38+G41+G44+G47 -> 48 | I50: =I51+I52 -> 48 | J50: =I38+I41+I44+I47 -> 48 | K50: =K51+K52 -> 48 | L50: =K38+K41+K44+K47 -> 48
B51: FT | C51: =C39+C42+C48+C45 -> 20 | E51: =E39+E42+E48+E45 -> 20 | G51: =G39+G42+G48+G45 -> 20 | I51: =I39+I42+I48+I45 -> 20 | K51: =K39+K42+K48+K45 -> 20
B52: PT | C52: =C40+C43+C49+C46 -> 28 | E52: =E40+E43+E49+E46 -> 28 | G52: =G40+G43+G49+G46 -> 28 | I52: =I40+I43+I49+I46 -> 28 | K52: =K40+K43+K49+K46 -> 28
